Workbook

Sheet 00_Instrucciones
A1: Plantilla Bloomberg HISTORICA — 1985-01-01 a 2026-05-29
A3: Que es esto
A4: Carga UNICA (una sola vez) de la serie historica diaria de tasas, swaps, TIPS, breakevens y futuros.
A5: Esto alimenta el backtest del modelo predictivo (1985+) y los graficos de 12M corridos de cada corte.
A6: NO es una plantilla recurrente — se corre una vez y se devuelve.
A8: Como usarlo (paso a paso)
A9: 1. Abrir el archivo en Excel con Bloomberg add-in activo.
A10: 2. En la hoja '01_Parametros', las fechas FROM_DATE y TO_DATE YA estan fijadas.
A11: NO usar =TODAY() — el TO_DATE es fecha literal del cierre del mes corriente.
A12: 3. Llenar ANALISTA (B5) y FECHA_CARGA (B6, fecha en que corres Bloomberg).
A13: 4. CADA HOJA DE DATOS tiene una formula =BDH en celda A4 con rango (FROM_DATE, TO_DATE).
A14: La formula se desborda automaticamente como tabla de 2 columnas (fecha, valor) por instrumento.
... A40: ALT 20Y: 5-10 minutos. Tamaño final ~5-10 MB.

Sheet 01_Parametros
A1: Parametros del backfill historico
A2: Parametro | B2: Valor | C2: Tipo | D2: Descripcion
A3: FROM_DATE | B3: 1985-01-01 | C3: fixed | D3: Inicio de la serie historica — literal, NO formula
A4: TO_DATE | B4: 2026-05-29 | C4: fixed | D4: Fin de la serie historica — literal, ajustar antes de correr
A5: ANALISTA | C5: input | D5: Nombre del analista que corre la plantilla
A6: FECHA_CARGA | C6: input | D6: Fecha de carga — escribir a mano (NO =TODAY())
A7: FECHA_GUARDADO_VALUES | C7: input | D7: Fecha del Paste Special -> Values — manual
A8: VERSION_PLANTILLA | B8: FULL o ALT_20Y | C8: fixed | D8: FULL = 1985-presente, ALT_20Y = ~20 anos
A9: NOTAS | C9: input | D9: Observaciones, tickers fallidos, etc.

Sheet UST_Nominal
A1: Categoria: UST_Nominal
A2: Cada instrumento ocupa 2 columnas (fecha, valor). La formula =BDH en fila 4 se desborda hacia abajo automaticamente.
A3: UST_1M — fecha | B3: UST_1M — valor | C3: UST_3M — fecha | D3: UST_3M — valor | E3: UST_6M — fecha | F3: UST_6M — valor | G3: UST_1Y — fecha | H3: UST_1Y — valor | I3: UST_2Y — fecha | J3: UST_2Y — valor | K3: UST_3Y — fecha | L3: UST_3Y — valor | M3: UST_5Y — fecha | N3: UST_5Y — valor | O3: UST_7Y — fecha | P3: UST_7Y — valor | Q3: UST_10Y — fecha | R3: UST_10Y — valor | S3: UST_20Y — fecha | T3: UST_20Y — valor | U3: UST_30Y — fecha | V3: UST_30Y — valor
A4: =BDH("USGG1M Index","PX_LAST",'01_Parametros'!$B$3,'01_Parametros'!$B$4,"Dir=V","Dts=H","Fill=B","cols=2;rows=12000") | C4: =BDH("USGG3M Index","PX_LAST",'01_Parametros'!$B$3,'01_Parametros'!$B$4,"Dir=V","Dts=H","Fill=B","cols=2;rows=12000") | E4: =BDH("USGG6M Index","PX_LAST",'01_Parametros'!$B$3,'01_Parametros'!$B$4,"Dir=V","Dts=H","Fill=B","cols=2;rows=12000") | G4: =BDH("USGG12M Index","PX_LAST",'01_Parametros'!$B$3,'01_Parametros'!$B$4,"Dir=V","Dts=H","Fill=B","cols=2;rows=12000") | I4: =BDH("USGG2YR Index","PX_LAST",'01_Parametros'!$B$3,'01_Parametros'!$B$4,"Dir=V","Dts=H","Fill=B","cols=2;rows=12000") | K4: =BDH("USGG3YR Index","PX_LAST",'01_Parametros'!$B$3,'01_Parametros'!$B$4,"Dir=V","Dts=H","Fill=B","cols=2;rows=12000") | M4: =BDH("USGG5YR Index","PX_LAST",'01_Parametros'!$B$3,'01_Parametros'!$B$4,"Dir=V","Dts=H","Fill=B","cols=2;rows=12000") | O4: =BDH("USGG7YR Index","PX_LAST",'01_Parametros'!$B$3,'01_Parametros'!$B$4,"Dir=V","Dts=H","Fill=B","cols=2;rows=12000") | Q4: =BDH("USGG10YR Index","PX_LAST",'01_Parametros'!$B$3,'01_Parametros'!$B$4,"Dir=V","Dts=H","Fill=B","cols=2;rows=12000") | S4: =BDH("USGG20YR Index","PX_LAST",'01_Parametros'!$B$3,'01_Parametros'!$B$4,"Dir=V","Dts=H","Fill=B","cols=2;rows=12000") | U4: =BDH("USGG30YR Index","PX_LAST",'01_Parametros'!$B$3,'01_Parametros'!$B$4,"Dir=V","Dts=H","Fill=B","cols=2;rows=12000")
A5: Ticker: USGG1M Index | B5: US Treasury 1M nominal | C5: Ticker: USGG3M Index | D5: US Treasury 3M nominal | E5: Ticker: USGG6M Index | F5: US Treasury 6M nominal | G5: Ticker: USGG12M Index | H5: US Treasury 1Y nominal | I5: Ticker: USGG2YR Index | J5: US Treasury 2Y nominal | K5: Ticker: USGG3YR Index | L5: US Treasury 3Y nominal | M5: Ticker: USGG5YR Index | N5: US Treasury 5Y nominal | O5: Ticker: USGG7YR Index | P5: US Treasury 7Y nominal | Q5: Ticker: USGG10YR Index | R5: US Treasury 10Y nominal | S5: Ticker: USGG20YR Index | T5: US Treasury 20Y nominal — gap 2002-2006 | U5: Ticker: USGG30YR Index | V5: US Treasury 30Y nominal — gap 2002-2006

Sheet TIPS_Real
A1: Categoria: TIPS_Real
A2: Cada instrumento ocupa 2 columnas (fecha, valor). La formula =BDH en fila 4 se desborda hacia abajo automaticamente.
A3: TIPS_5Y — fecha | B3: TIPS_5Y — valor | C3: TIPS_10Y — fecha | D3: TIPS_10Y — valor | E3: TIPS_20Y — fecha | F3: TIPS_20Y — valor | G3: TIPS_30Y — fecha | H3: TIPS_30Y — valor
A4: =BDH("USGGT05Y Index","PX_LAST",'01_Parametros'!$B$3,'01_Parametros'!$B$4,"Dir=V","Dts=H","Fill=B","cols=2;rows=12000") | C4: =BDH("USGGT10Y Index","PX_LAST",'01_Parametros'!$B$3,'01_Parametros'!$B$4,"Dir=V","Dts=H","Fill=B","cols=2;rows=12000") | E4: =BDH("USGGT20Y Index","PX_LAST",'01_Parametros'!$B$3,'01_Parametros'!$B$4,"Dir=V","Dts=H","Fill=B","cols=2;rows=12000") | G4: =BDH("USGGT30Y Index","PX_LAST",'01_Parametros'!$B$3,'01_Parametros'!$B$4,"Dir=V","Dts=H","Fill=B","cols=2;rows=12000")
A5: Ticker: USGGT05Y Index | B5: TIPS 5Y CMT — disponible desde 2003 | C5: Ticker: USGGT10Y Index | D5: TIPS 10Y CMT — disponible desde 2003 | E5: Ticker: USGGT20Y Index | F5: TIPS 20Y CMT — disponible desde 2004 | G5: Ticker: USGGT30Y Index | H5: TIPS 30Y CMT — disponible desde 2010

Sheet Breakevens
A1: Categoria: Breakevens
A2: Cada instrumento ocupa 2 columnas (fecha, valor). La formula =BDH en fila 4 se desborda hacia abajo automaticamente.
A3: BE_2Y — fecha | B3: BE_2Y — valor | C3: BE_5Y — fecha | D3: BE_5Y — valor | E3: BE_10Y — fecha | F3: BE_10Y — valor | G3: BE_30Y — fecha | H3: BE_30Y — valor
A4: =BDH("USGGBE02 Index","PX_LAST",'01_Parametros'!$B$3,'01_Parametros'!$B$4,"Dir=V","Dts=H","Fill=B","cols=2;rows=12000") | C4: =BDH("USGGBE05 Index","PX_LAST",'01_Parametros'!$B$3,'01_Parametros'!$B$4,"Dir=V","Dts=H","Fill=B","cols=2;rows=12000") | E4: =BDH("USGGBE10 Index","PX_LAST",'01_Parametros'!$B$3,'01_Parametros'!$B$4,"Dir=V","Dts=H","Fill=B","cols=2;rows=12000") | G4: =BDH("USGGBE30 Index","PX_LAST",'01_Parametros'!$B$3,'01_Parametros'!$B$4,"Dir=V","Dts=H","Fill=B","cols=2;rows=12000")
A5: Ticker: USGGBE02 Index | B5: US 2Y breakeven inflation | C5: Ticker: USGGBE05 Index | D5: US 5Y breakeven inflation | E5: Ticker: USGGBE10 Index | F5: US 10Y breakeven inflation | G5: Ticker: USGGBE30 Index | H5: US 30Y breakeven inflation

Sheet Swap_SOFR_OIS
A1: Categoria: Swap_SOFR_OIS
A2: Cada instrumento ocupa 2 columnas (fecha, valor). La formula =BDH en fila 4 se desborda hacia abajo automaticamente.
A3: SOFR_OIS_2Y — fecha | B3: SOFR_OIS_2Y — valor | C3: SOFR_OIS_5Y — fecha | D3: SOFR_OIS_5Y — valor | E3: SOFR_OIS_10Y — fecha | F3: SOFR_OIS_10Y — valor | G3: SOFR_OIS_30Y — fecha | H3: SOFR_OIS_30Y — valor
A4: =BDH("USOSFR2 BGN Curncy","PX_LAST",'01_Parametros'!$B$3,'01_Parametros'!$B$4,"Dir=V","Dts=H","Fill=B","cols=2;rows=12000") | C4: =BDH("USOSFR5 BGN Curncy","PX_LAST",'01_Parametros'!$B$3,'01_Parametros'!$B$4,"Dir=V","Dts=H","Fill=B","cols=2;rows=12000") | E4: =BDH("USOSFR10 BGN Curncy","PX_LAST",'01_Parametros'!$B$3,'01_Parametros'!$B$4,"Dir=V","Dts=H","Fill=B","cols=2;rows=12000") | G4: =BDH("USOSFR30 BGN Curncy","PX_LAST",'01_Parametros'!$B$3,'01_Parametros'!$B$4,"Dir=V","Dts=H","Fill=B","cols=2;rows=12000")
A5: Ticker: USOSFR2 BGN Curncy | B5: USD SOFR OIS 2Y - confirmar conv | C5: Ticker: USOSFR5 BGN Curncy | D5: USD SOFR OIS 5Y - confirmar conv | E5: Ticker: USOSFR10 BGN Curncy | F5: USD SOFR OIS 10Y - confirmar conv | G5: Ticker: USOSFR30 BGN Curncy | H5: USD SOFR OIS 30Y - confirmar conv

Sheet Swap_USD_Clasico_LIBOR
A1: Categoria: Swap_USD_Clasico_LIBOR
A2: Cada instrumento ocupa 2 columnas (fecha, valor). La formula =BDH en fila 4 se desborda hacia abajo automaticamente.
A3: USSW2_LIBOR — fecha | B3: USSW2_LIBOR — valor | C3: USSW5_LIBOR — fecha | D3: USSW5_LIBOR — valor | E3: USSW10_LIBOR — fecha | F3: USSW10_LIBOR — valor | G3: USSW30_LIBOR — fecha | H3: USSW30_LIBOR — valor
A4: =BDH("USSW2 Curncy","PX_LAST",'01_Parametros'!$B$3,'01_Parametros'!$B$4,"Dir=V","Dts=H","Fill=B","cols=2;rows=12000") | C4: =BDH("USSW5 Curncy","PX_LAST",'01_Parametros'!$B$3,'01_Parametros'!$B$4,"Dir=V","Dts=H","Fill=B","cols=2;rows=12000") | E4: =BDH("USSW10 Curncy","PX_LAST",'01_Parametros'!$B$3,'01_Parametros'!$B$4,"Dir=V","Dts=H","Fill=B","cols=2;rows=12000") | G4: =BDH("USSW30 Curncy","PX_LAST",'01_Parametros'!$B$3,'01_Parametros'!$B$4,"Dir=V","Dts=H","Fill=B","cols=2;rows=12000")
A5: Ticker: USSW2 Curncy | B5: USD swap 2Y LIBOR-based (pre-SOFR proxy) | C5: Ticker: USSW5 Curncy | D5: USD swap 5Y LIBOR-based | E5: Ticker: USSW10 Curncy | F5: USD swap 10Y LIBOR-based | G5: Ticker: USSW30 Curncy | H5: USD swap 30Y LIBOR-based

Sheet SOFR_Money_Market
A1: Categoria: SOFR_Money_Market
A2: Cada instrumento ocupa 2 columnas (fecha, valor). La formula =BDH en fila 4 se desborda hacia abajo automaticamente.
A3: SOFR_ON — fecha | B3: SOFR_ON — valor | C3: SOFR_30D_AVG — fecha | D3: SOFR_30D_AVG — valor | E3: SOFR_90D_AVG — fecha | F3: SOFR_90D_AVG — valor | G3: TERM_SOFR_1M — fecha | H3: TERM_SOFR_1M — valor | I3: TERM_SOFR_3M — fecha | J3: TERM_SOFR_3M — valor | K3: TERM_SOFR_6M — fecha | L3: TERM_SOFR_6M — valor | M3: TERM_SOFR_12M — fecha | N3: TERM_SOFR_12M — valor
A4: =BDH("SOFRRATE Index","PX_LAST",'01_Parametros'!$B$3,'01_Parametros'!$B$4,"Dir=V","Dts=H","Fill=B","cols=2;rows=12000") | C4: =BDH("SOFR30A Index","PX_LAST",'01_Parametros'!$B$3,'01_Parametros'!$B$4,"Dir=V","Dts=H","Fill=B","cols=2;rows=12000") | E4: =BDH("SOFR90A Index","PX_LAST",'01_Parametros'!$B$3,'01_Parametros'!$B$4,"Dir=V","Dts=H","Fill=B","cols=2;rows=12000") | G4: =BDH("USOSFR1Z BGN Curncy","PX_LAST",'01_Parametros'!$B$3,'01_Parametros'!$B$4,"Dir=V","Dts=H","Fill=B","cols=2;rows=12000") | I4: =BDH("USOSFR3Z BGN Curncy","PX_LAST",'01_Parametros'!$B$3,'01_Parametros'!$B$4,"Dir=V","Dts=H","Fill=B","cols=2;rows=12000") | K4: =BDH("USOSFR6Z BGN Curncy","PX_LAST",'01_Parametros'!$B$3,'01_Parametros'!$B$4,"Dir=V","Dts=H","Fill=B","cols=2;rows=12000") | M4: =BDH("USOSFR12Z BGN Curncy","PX_LAST",'01_Parametros'!$B$3,'01_Parametros'!$B$4,"Dir=V","Dts=H","Fill=B","cols=2;rows=12000")
A5: Ticker: SOFRRATE Index | B5: SOFR overnight - desde 2018-04 | C5: Ticker: SOFR30A Index | D5: SOFR 30-day average | E5: Ticker: SOFR90A Index | F5: SOFR 90-day average | G5: Ticker: USOSFR1Z BGN Curncy | H5: Term SOFR 1M | I5: Ticker: USOSFR3Z BGN Curncy | J5: Term SOFR 3M | K5: Ticker: USOSFR6Z BGN Curncy | L5: Term SOFR 6M | M5: Ticker: USOSFR12Z BGN Curncy | N5: Term SOFR 12M

Sheet FedFunds_Policy
A1: Categoria: FedFunds_Policy
A2: Cada instrumento ocupa 2 columnas (fecha, valor). La formula =BDH en fila 4 se desborda hacia abajo automaticamente.
A3: FED_FUNDS_UPPER — fecha | B3: FED_FUNDS_UPPER — valor | C3: FED_FUNDS_LOWER — fecha | D3: FED_FUNDS_LOWER — valor | E3: FED_FUNDS_TARGET_PRE2008 — fecha | F3: FED_FUNDS_TARGET_PRE2008 — valor | G3: EFFR — fecha | H3: EFFR — valor | I3: IORB — fecha | J3: IORB — valor | K3: ON_RRP — fecha | L3: ON_RRP — valor
A4: =BDH("FDTR Index","PX_LAST",'01_Parametros'!$B$3,'01_Parametros'!$B$4,"Dir=V","Dts=H","Fill=B","cols=2;rows=12000") | C4: =BDH("FDFD Index","PX_LAST",'01_Parametros'!$B$3,'01_Parametros'!$B$4,"Dir=V","Dts=H","Fill=B","cols=2;rows=12000") | E4: =BDH("FEDFUND Index","PX_LAST",'01_Parametros'!$B$3,'01_Parametros'!$B$4,"Dir=V","Dts=H","Fill=B","cols=2;rows=12000") | G4: =BDH("FEDL01 Index","PX_LAST",'01_Parametros'!$B$3,'01_Parametros'!$B$4,"Dir=V","Dts=H","Fill=B","cols=2;rows=12000") | I4: =BDH("FRRRIORB Index","PX_LAST",'01_Parametros'!$B$3,'01_Parametros'!$B$4,"Dir=V","Dts=H","Fill=B","cols=2;rows=12000") | K4: =BDH("RRPONTSY Index","PX_LAST",'01_Parametros'!$B$3,'01_Parametros'!$B$4,"Dir=V","Dts=H","Fill=B","cols=2;rows=12000")
A5: Ticker: FDTR Index | B5: Fed Funds Target Upper Bound (post-2008) | C5: Ticker: FDFD Index | D5: Fed Funds Target Lower Bound - confirmar | E5: Ticker: FEDFUND Index | F5: Fed Funds Target unico (pre-Dec-2008) - confirmar | G5: Ticker: FEDL01 Index | H5: Effective Fed Funds Rate | I5: Ticker: FRRRIORB Index | J5: Interest on Reserve Balances - desde 2008 | K5: Ticker: RRPONTSY Index | L5: Overnight Reverse Repo

Sheet EuroDollar_Futures_Proxy_PreSOF
A1: Categoria: EuroDollar_Futures_Proxy_PreSOFR
A2: Cada instrumento ocupa 2 columnas (fecha, valor). La formula =BDH en fila 4 se desborda hacia abajo automaticamente.
A3: ED_1Q — fecha | B3: ED_1Q — valor | C3: ED_2Q — fecha | D3: ED_2Q — valor | E3: ED_3Q — fecha | F3: ED_3Q — valor | G3: ED_4Q — fecha | H3: ED_4Q — valor | I3: ED_5Q — fecha | J3: ED_5Q — valor | K3: ED_6Q — fecha | L3: ED_6Q — valor | M3: ED_7Q — fecha | N3: ED_7Q — valor | O3: ED_8Q — fecha | P3: ED_8Q — valor
A4: =BDH("ED1 Comdty","PX_LAST",'01_Parametros'!$B$3,'01_Parametros'!$B$4,"Dir=V","Dts=H","Fill=B","cols=2;rows=12000") | C4: =BDH("ED2 Comdty","PX_LAST",'01_Parametros'!$B$3,'01_Parametros'!$B$4,"Dir=V","Dts=H","Fill=B","cols=2;rows=12000") | E4: =BDH("ED3 Comdty","PX_LAST",'01_Parametros'!$B$3,'01_Parametros'!$B$4,"Dir=V","Dts=H","Fill=B","cols=2;rows=12000") | G4: =BDH("ED4 Comdty","PX_LAST",'01_Parametros'!$B$3,'01_Parametros'!$B$4,"Dir=V","Dts=H","Fill=B","cols=2;rows=12000") | I4: =BDH("ED5 Comdty","PX_LAST",'01_Parametros'!$B$3,'01_Parametros'!$B$4,"Dir=V","Dts=H","Fill=B","cols=2;rows=12000") | K4: =BDH("ED6 Comdty","PX_LAST",'01_Parametros'!$B$3,'01_Parametros'!$B$4,"Dir=V","Dts=H","Fill=B","cols=2;rows=12000") | M4: =BDH("ED7 Comdty","PX_LAST",'01_Parametros'!$B$3,'01_Parametros'!$B$4,"Dir=V","Dts=H","Fill=B","cols=2;rows=12000") | O4: =BDH("ED8 Comdty","PX_LAST",'01_Parametros'!$B$3,'01_Parametros'!$B$4,"Dir=V","Dts=H","Fill=B","cols=2;rows=12000")
A5: Ticker: ED1 Comdty | B5: EuroDollar continuous 1st quarter (pre-SOFR proxy) | C5: Ticker: ED2 Comdty | D5: EuroDollar continuous 2nd | E5: Ticker: ED3 Comdty | F5: EuroDollar continuous 3rd | G5: Ticker: ED4 Comdty | H5: EuroDollar continuous 4th | I5: Ticker: ED5 Comdty | J5: EuroDollar continuous 5th | K5: Ticker: ED6 Comdty | L5: EuroDollar continuous 6th | M5: Ticker: ED7 Comdty | N5: EuroDollar continuous 7th | O5: Ticker: ED8 Comdty | P5: EuroDollar continuous 8th

Sheet SR3_SOFR_Futures
A1: Categoria: SR3_SOFR_Futures
A2: Cada instrumento ocupa 2 columnas (fecha, valor). La formula =BDH en fila 4 se desborda hacia abajo automaticamente.
A3: SR3_1Q — fecha | B3: SR3_1Q — valor | C3: SR3_2Q — fecha | D3: SR3_2Q — valor | E3: SR3_3Q — fecha | F3: SR3_3Q — valor | G3: SR3_4Q — fecha | H3: SR3_4Q — valor | I3: SR3_5Q — fecha | J3: SR3_5Q — valor | K3: SR3_6Q — fecha | L3: SR3_6Q — valor | M3: SR3_7Q — fecha | N3: SR3_7Q — valor | O3: SR3_8Q — fecha | P3: SR3_8Q — valor
A4: =BDH("SFR1 Comdty","PX_LAST",'01_Parametros'!$B$3,'01_Parametros'!$B$4,"Dir=V","Dts=H","Fill=B","cols=2;rows=12000") | C4: =BDH("SFR2 Comdty","PX_LAST",'01_Parametros'!$B$3,'01_Parametros'!$B$4,"Dir=V","Dts=H","Fill=B","cols=2;rows=12000") | E4: =BDH("SFR3 Comdty","PX_LAST",'01_Parametros'!$B$3,'01_Parametros'!$B$4,"Dir=V","Dts=H","Fill=B","cols=2;rows=12000") | G4: =BDH("SFR4 Comdty","PX_LAST",'01_Parametros'!$B$3,'01_Parametros'!$B$4,"Dir=V","Dts=H","Fill=B","cols=2;rows=12000") | I4: =BDH("SFR5 Comdty","PX_LAST",'01_Parametros'!$B$3,'01_Parametros'!$B$4,"Dir=V","Dts=H","Fill=B","cols=2;rows=12000") | K4: =BDH("SFR6 Comdty","PX_LAST",'01_Parametros'!$B$3,'01_Parametros'!$B$4,"Dir=V","Dts=H","Fill=B","cols=2;rows=12000") | M4: =BDH("SFR7 Comdty","PX_LAST",'01_Parametros'!$B$3,'01_Parametros'!$B$4,"Dir=V","Dts=H","Fill=B","cols=2;rows=12000") | O4: =BDH("SFR8 Comdty","PX_LAST",'01_Parametros'!$B$3,'01_Parametros'!$B$4,"Dir=V","Dts=H","Fill=B","cols=2;rows=12000")
A5: Ticker: SFR1 Comdty | B5: SOFR future month 1 | C5: Ticker: SFR2 Comdty | D5: SOFR future month 2 | E5: Ticker: SFR3 Comdty | F5: SOFR future month 3 | G5: Ticker: SFR4 Comdty | H5: SOFR future month 4 | I5: Ticker: SFR5 Comdty | J5: SOFR future month 5 | K5: Ticker: SFR6 Comdty | L5: SOFR future month 6 | M5: Ticker: SFR7 Comdty | N5: SOFR future month 7 | O5: Ticker: SFR8 Comdty | P5: SOFR future month 8

Sheet 05_Notas_Analista
A1: Notas del analista
A3: Tickers que fallaron, series con gaps inesperados, sugerencias, observaciones de carga.
A5: Tickers fallidos / corregidos
A21: Series con datos faltantes inesperados
A31: Observaciones de carga

Sheet 99_Envio
A1: Como devolver este archivo
A3: OPCION 1 — Recomendada — Upload directo a GitHub (web)
A4: 1. Guardar con sufijo FULL o ALT_20Y segun corresponda.
A5: 2. Ir a github.com/andresborrerom/credito_Panama, branch claude/tasas-mercantil-report-Q8sFt.
A6: 3. Navegar a ProyectoTasasMercantil/plantilla_bloomberg/historico/.
A7: 4. Add file -> Upload files -> arrastrar el xlsx.
A8: 5. Commit message: 'historico: carga Bloomberg <FULL|ALT_20Y> por <analista>'.
A10: OPCION 2 — Correo
A11: Adjuntar y mandar a Andres. Asunto: 'Tasas Mercantil — Carga historica Bloomberg <FULL|ALT_20Y>'.
