Workbook

Sheet 00_Instrucciones
A1: Plantilla Bloomberg — Reporte Mensual de Tasas Mercantil
A3: Que es esto
A4: Plantilla que se corre cada mes para extraer datos de Bloomberg al cierre del ultimo dia habil.
A5: Output: este mismo archivo con valores cuajados (no formulas vivas).
A7: LECCION DEL PROYECTO HERMANO (mercantil-saa) — IMPORTANTE
A8: NO usar 'today' como string en formulas BDH (=BDH(...,'today',...)).
A9: NO usar =TODAY() en ninguna celda del archivo.
A10: Ambos se RECALCULAN al reabrir el archivo y rompen la reproducibilidad: los datos del
A11: snapshot del cierre de mes pueden mutarse a la fecha en que alguien lo abre semanas despues.
A12: La plantilla esta diseñada para evitar esto: todas las formulas referencian la celda AS_OF de
A13: la hoja 01_Parametros, que es input manual fijo. Aun asi, el paso de Paste Special -> Values
A14: antes de devolver el archivo es OBLIGATORIO. Vea el paso 9 abajo.
... A55: Total: ~5 minutos por corte.

Sheet 01_Parametros
A1: Parametros del corte
A2: Parametro | B2: Valor | C2: Tipo | D2: Descripcion
A3: AS_OF | C3: input | D3: Ultimo dia habil del mes a reportar — EDITAR esta celda
A4: MES_REPORTE | B4: =TEXT(B3,"yyyy-mm") | C4: auto | D4: YYYY-MM del corte
A5: MES_ANT | B5: =EOMONTH(B3,-1) | C5: auto | D5: Ultimo dia del mes anterior
A6: YE_ANT | B6: =DATE(YEAR(B3)-1,12,31) | C6: auto | D6: 31-dic del año anterior
A7: INI_12M | B7: =EDATE(B3,-12) | C7: auto | D7: 12 meses antes de AS_OF
A8: ANALISTA | C8: input | D8: Nombre del analista que corre la plantilla
A9: FECHA_CARGA | C9: input | D9: Fecha en que se cargaron los datos — ESCRIBIR a mano (NO =TODAY())
A10: FECHA_GUARDADO_VALUES | C10: input | D10: Fecha en que se hizo Paste Special -> Values — ESCRIBIR a mano
A11: BBG_UUID | C11: input | D11: BBG UUID (opcional)
A12: NOTAS_RAPIDAS | C12: input | D12: Cualquier anomalia detectada al cargar

Sheet 02_Datos
A1: # | B1: categoria | C1: region | D1: instrument | E1: tenor_label | F1: tenor_years | G1: ticker | H1: field | I1: unit | J1: val_AS_OF | K1: val_MES_ANT | L1: val_YE_ANT | M1: val_INI_12M | N1: nota
A2: 1 | B2: policy | C2: US | D2: FED_FUNDS_UPPER | E2: — | F2: 0 | G2: FDTR Index | H2: PX_LAST | I2: percent | J2: =IFERROR(INDEX(BDH($G$2,$H$2,'01_Parametros'!$B$3,'01_Parametros'!$B$3,"Days=A","Fill=B","Dir=H"),1,2),BDH($G$2,$H$2,'01_Parametros'!$B$3,'01_Parametros'!$B$3,"Days=A","Fill=B")) | K2: =IFERROR(INDEX(BDH($G$2,$H$2,'01_Parametros'!$B$5,'01_Parametros'!$B$5,"Days=A","Fill=B","Dir=H"),1,2),BDH($G$2,$H$2,'01_Parametros'!$B$5,'01_Parametros'!$B$5,"Days=A","Fill=B")) | L2: =IFERROR(INDEX(BDH($G$2,$H$2,'01_Parametros'!$B$6,'01_Parametros'!$B$6,"Days=A","Fill=B","Dir=H"),1,2),BDH($G$2,$H$2,'01_Parametros'!$B$6,'01_Parametros'!$B$6,"Days=A","Fill=B")) | M2: =IFERROR(INDEX(BDH($G$2,$H$2,'01_Parametros'!$B$7,'01_Parametros'!$B$7,"Days=A","Fill=B","Dir=H"),1,2),BDH($G$2,$H$2,'01_Parametros'!$B$7,'01_Parametros'!$B$7,"Days=A","Fill=B")) | N2: Fed Funds Target Upper Bound
A3: 2 | B3: policy | C3: US | D3: FED_FUNDS_LOWER | E3: — | F3: 0 | G3: FDFD Index | H3: PX_LAST | I3: percent | J3: =IFERROR(INDEX(BDH($G$3,$H$3,'01_Parametros'!$B$3,'01_Parametros'!$B$3,"Days=A","Fill=B","Dir=H"),1,2),BDH($G$3,$H$3,'01_Parametros'!$B$3,'01_Parametros'!$B$3,"Days=A","Fill=B")) | K3: =IFERROR(INDEX(BDH($G$3,$H$3,'01_Parametros'!$B$5,'01_Parametros'!$B$5,"Days=A","Fill=B","Dir=H"),1,2),BDH($G$3,$H$3,'01_Parametros'!$B$5,'01_Parametros'!$B$5,"Days=A","Fill=B")) | L3: =IFERROR(INDEX(BDH($G$3,$H$3,'01_Parametros'!$B$6,'01_Parametros'!$B$6,"Days=A","Fill=B","Dir=H"),1,2),BDH($G$3,$H$3,'01_Parametros'!$B$6,'01_Parametros'!$B$6,"Days=A","Fill=B")) | M3: =IFERROR(INDEX(BDH($G$3,$H$3,'01_Parametros'!$B$7,'01_Parametros'!$B$7,"Days=A","Fill=B","Dir=H"),1,2),BDH($G$3,$H$3,'01_Parametros'!$B$7,'01_Parametros'!$B$7,"Days=A","Fill=B")) | N3: Fed Funds Target Lower Bound — confirmar ticker
A4: 3 | B4: policy | C4: US | D4: EFFR | E4: ON | F4: 0 | G4: FEDL01 Index | H4: PX_LAST | I4: percent | J4: =IFERROR(INDEX(BDH($G$4,$H$4,'01_Parametros'!$B$3,'01_Parametros'!$B$3,"Days=A","Fill=B","Dir=H"),1,2),BDH($G$4,$H$4,'01_Parametros'!$B$3,'01_Parametros'!$B$3,"Days=A","Fill=B")) | K4: =IFERROR(INDEX(BDH($G$4,$H$4,'01_Parametros'!$B$5,'01_Parametros'!$B$5,"Days=A","Fill=B","Dir=H"),1,2),BDH($G$4,$H$4,'01_Parametros'!$B$5,'01_Parametros'!$B$5,"Days=A","Fill=B")) | L4: =IFERROR(INDEX(BDH($G$4,$H$4,'01_Parametros'!$B$6,'01_Parametros'!$B$6,"Days=A","Fill=B","Dir=H"),1,2),BDH($G$4,$H$4,'01_Parametros'!$B$6,'01_Parametros'!$B$6,"Days=A","Fill=B")) | M4: =IFERROR(INDEX(BDH($G$4,$H$4,'01_Parametros'!$B$7,'01_Parametros'!$B$7,"Days=A","Fill=B","Dir=H"),1,2),BDH($G$4,$H$4,'01_Parametros'!$B$7,'01_Parametros'!$B$7,"Days=A","Fill=B")) | N4: Effective Fed Funds Rate
A5: 4 | B5: policy | C5: US | D5: IORB | E5: — | F5: 0 | G5: FRRRIORB Index | H5: PX_LAST | I5: percent | J5: =IFERROR(INDEX(BDH($G$5,$H$5,'01_Parametros'!$B$3,'01_Parametros'!$B$3,"Days=A","Fill=B","Dir=H"),1,2),BDH($G$5,$H$5,'01_Parametros'!$B$3,'01_Parametros'!$B$3,"Days=A","Fill=B")) | K5: =IFERROR(INDEX(BDH($G$5,$H$5,'01_Parametros'!$B$5,'01_Parametros'!$B$5,"Days=A","Fill=B","Dir=H"),1,2),BDH($G$5,$H$5,'01_Parametros'!$B$5,'01_Parametros'!$B$5,"Days=A","Fill=B")) | L5: =IFERROR(INDEX(BDH($G$5,$H$5,'01_Parametros'!$B$6,'01_Parametros'!$B$6,"Days=A","Fill=B","Dir=H"),1,2),BDH($G$5,$H$5,'01_Parametros'!$B$6,'01_Parametros'!$B$6,"Days=A","Fill=B")) | M5: =IFERROR(INDEX(BDH($G$5,$H$5,'01_Parametros'!$B$7,'01_Parametros'!$B$7,"Days=A","Fill=B","Dir=H"),1,2),BDH($G$5,$H$5,'01_Parametros'!$B$7,'01_Parametros'!$B$7,"Days=A","Fill=B")) | N5: Interest on Reserve Balances
A6: 5 | B6: policy | C6: US | D6: ON_RRP | E6: ON | F6: 0 | G6: RRPONTSY Index | H6: PX_LAST | I6: percent | J6: =IFERROR(INDEX(BDH($G$6,$H$6,'01_Parametros'!$B$3,'01_Parametros'!$B$3,"Days=A","Fill=B","Dir=H"),1,2),BDH($G$6,$H$6,'01_Parametros'!$B$3,'01_Parametros'!$B$3,"Days=A","Fill=B")) | K6: =IFERROR(INDEX(BDH($G$6,$H$6,'01_Parametros'!$B$5,'01_Parametros'!$B$5,"Days=A","Fill=B","Dir=H"),1,2),BDH($G$6,$H$6,'01_Parametros'!$B$5,'01_Parametros'!$B$5,"Days=A","Fill=B")) | L6: =IFERROR(INDEX(BDH($G$6,$H$6,'01_Parametros'!$B$6,'01_Parametros'!$B$6,"Days=A","Fill=B","Dir=H"),1,2),BDH($G$6,$H$6,'01_Parametros'!$B$6,'01_Parametros'!$B$6,"Days=A","Fill=B")) | M6: =IFERROR(INDEX(BDH($G$6,$H$6,'01_Parametros'!$B$7,'01_Parametros'!$B$7,"Days=A","Fill=B","Dir=H"),1,2),BDH($G$6,$H$6,'01_Parametros'!$B$7,'01_Parametros'!$B$7,"Days=A","Fill=B")) | N6: Overnight Reverse Repo
A7: 6 | B7: money_market | C7: US | D7: SOFR_ON | E7: ON | F7: 0.003 | G7: SOFRRATE Index | H7: PX_LAST | I7: percent | J7: =IFERROR(INDEX(BDH($G$7,$H$7,'01_Parametros'!$B$3,'01_Parametros'!$B$3,"Days=A","Fill=B","Dir=H"),1,2),BDH($G$7,$H$7,'01_Parametros'!$B$3,'01_Parametros'!$B$3,"Days=A","Fill=B")) | K7: =IFERROR(INDEX(BDH($G$7,$H$7,'01_Parametros'!$B$5,'01_Parametros'!$B$5,"Days=A","Fill=B","Dir=H"),1,2),BDH($G$7,$H$7,'01_Parametros'!$B$5,'01_Parametros'!$B$5,"Days=A","Fill=B")) | L7: =IFERROR(INDEX(BDH($G$7,$H$7,'01_Parametros'!$B$6,'01_Parametros'!$B$6,"Days=A","Fill=B","Dir=H"),1,2),BDH($G$7,$H$7,'01_Parametros'!$B$6,'01_Parametros'!$B$6,"Days=A","Fill=B")) | M7: =IFERROR(INDEX(BDH($G$7,$H$7,'01_Parametros'!$B$7,'01_Parametros'!$B$7,"Days=A","Fill=B","Dir=H"),1,2),BDH($G$7,$H$7,'01_Parametros'!$B$7,'01_Parametros'!$B$7,"Days=A","Fill=B")) | N7: SOFR overnight
A8: 7 | B8: money_market | C8: US | D8: SOFR_1M_AVG | E8: 1M_AVG | F8: 0.083 | G8: SOFR30A Index | H8: PX_LAST | I8: percent | J8: =IFERROR(INDEX(BDH($G$8,$H$8,'01_Parametros'!$B$3,'01_Parametros'!$B$3,"Days=A","Fill=B","Dir=H"),1,2),BDH($G$8,$H$8,'01_Parametros'!$B$3,'01_Parametros'!$B$3,"Days=A","Fill=B")) | K8: =IFERROR(INDEX(BDH($G$8,$H$8,'01_Parametros'!$B$5,'01_Parametros'!$B$5,"Days=A","Fill=B","Dir=H"),1,2),BDH($G$8,$H$8,'01_Parametros'!$B$5,'01_Parametros'!$B$5,"Days=A","Fill=B")) | L8: =IFERROR(INDEX(BDH($G$8,$H$8,'01_Parametros'!$B$6,'01_Parametros'!$B$6,"Days=A","Fill=B","Dir=H"),1,2),BDH($G$8,$H$8,'01_Parametros'!$B$6,'01_Parametros'!$B$6,"Days=A","Fill=B")) | M8: =IFERROR(INDEX(BDH($G$8,$H$8,'01_Parametros'!$B$7,'01_Parametros'!$B$7,"Days=A","Fill=B","Dir=H"),1,2),BDH($G$8,$H$8,'01_Parametros'!$B$7,'01_Parametros'!$B$7,"Days=A","Fill=B")) | N8: SOFR 30-day average
A9: 8 | B9: money_market | C9: US | D9: SOFR_3M_AVG | E9: 3M_AVG | F9: 0.25 | G9: SOFR90A Index | H9: PX_LAST | I9: percent | J9: =IFERROR(INDEX(BDH($G$9,$H$9,'01_Parametros'!$B$3,'01_Parametros'!$B$3,"Days=A","Fill=B","Dir=H"),1,2),BDH($G$9,$H$9,'01_Parametros'!$B$3,'01_Parametros'!$B$3,"Days=A","Fill=B")) | K9: =IFERROR(INDEX(BDH($G$9,$H$9,'01_Parametros'!$B$5,'01_Parametros'!$B$5,"Days=A","Fill=B","Dir=H"),1,2),BDH($G$9,$H$9,'01_Parametros'!$B$5,'01_Parametros'!$B$5,"Days=A","Fill=B")) | L9: =IFERROR(INDEX(BDH($G$9,$H$9,'01_Parametros'!$B$6,'01_Parametros'!$B$6,"Days=A","Fill=B","Dir=H"),1,2),BDH($G$9,$H$9,'01_Parametros'!$B$6,'01_Parametros'!$B$6,"Days=A","Fill=B")) | M9: =IFERROR(INDEX(BDH($G$9,$H$9,'01_Parametros'!$B$7,'01_Parametros'!$B$7,"Days=A","Fill=B","Dir=H"),1,2),BDH($G$9,$H$9,'01_Parametros'!$B$7,'01_Parametros'!$B$7,"Days=A","Fill=B")) | N9: SOFR 90-day average
A10: 9 | B10: money_market | C10: US | D10: TERM_SOFR_1M | E10: 1M | F10: 0.083 | G10: USOSFR1Z BGN Curncy | H10: PX_LAST | I10: percent | J10: =IFERROR(INDEX(BDH($G$10,$H$10,'01_Parametros'!$B$3,'01_Parametros'!$B$3,"Days=A","Fill=B","Dir=H"),1,2),BDH($G$10,$H$10,'01_Parametros'!$B$3,'01_Parametros'!$B$3,"Days=A","Fill=B")) | K10: =IFERROR(INDEX(BDH($G$10,$H$10,'01_Parametros'!$B$5,'01_Parametros'!$B$5,"Days=A","Fill=B","Dir=H"),1,2),BDH($G$10,$H$10,'01_Parametros'!$B$5,'01_Parametros'!$B$5,"Days=A","Fill=B")) | L10: =IFERROR(INDEX(BDH($G$10,$H$10,'01_Parametros'!$B$6,'01_Parametros'!$B$6,"Days=A","Fill=B","Dir=H"),1,2),BDH($G$10,$H$10,'01_Parametros'!$B$6,'01_Parametros'!$B$6,"Days=A","Fill=B")) | M10: =IFERROR(INDEX(BDH($G$10,$H$10,'01_Parametros'!$B$7,'01_Parametros'!$B$7,"Days=A","Fill=B","Dir=H"),1,2),BDH($G$10,$H$10,'01_Parametros'!$B$7,'01_Parametros'!$B$7,"Days=A","Fill=B")) | N10: Term SOFR 1M - CME
A11: 10 | B11: money_market | C11: US | D11: TERM_SOFR_3M | E11: 3M | F11: 0.25 | G11: USOSFR3Z BGN Curncy | H11: PX_LAST | I11: percent | J11: =IFERROR(INDEX(BDH($G$11,$H$11,'01_Parametros'!$B$3,'01_Parametros'!$B$3,"Days=A","Fill=B","Dir=H"),1,2),BDH($G$11,$H$11,'01_Parametros'!$B$3,'01_Parametros'!$B$3,"Days=A","Fill=B")) | K11: =IFERROR(INDEX(BDH($G$11,$H$11,'01_Parametros'!$B$5,'01_Parametros'!$B$5,"Days=A","Fill=B","Dir=H"),1,2),BDH($G$11,$H$11,'01_Parametros'!$B$5,'01_Parametros'!$B$5,"Days=A","Fill=B")) | L11: =IFERROR(INDEX(BDH($G$11,$H$11,'01_Parametros'!$B$6,'01_Parametros'!$B$6,"Days=A","Fill=B","Dir=H"),1,2),BDH($G$11,$H$11,'01_Parametros'!$B$6,'01_Parametros'!$B$6,"Days=A","Fill=B")) | M11: =IFERROR(INDEX(BDH($G$11,$H$11,'01_Parametros'!$B$7,'01_Parametros'!$B$7,"Days=A","Fill=B","Dir=H"),1,2),BDH($G$11,$H$11,'01_Parametros'!$B$7,'01_Parametros'!$B$7,"Days=A","Fill=B")) | N11: Term SOFR 3M - CME
A12: 11 | B12: money_market | C12: US | D12: TERM_SOFR_6M | E12: 6M | F12: 0.5 | G12: USOSFR6Z BGN Curncy | H12: PX_LAST | I12: percent | J12: =IFERROR(INDEX(BDH($G$12,$H$12,'01_Parametros'!$B$3,'01_Parametros'!$B$3,"Days=A","Fill=B","Dir=H"),1,2),BDH($G$12,$H$12,'01_Parametros'!$B$3,'01_Parametros'!$B$3,"Days=A","Fill=B")) | K12: =IFERROR(INDEX(BDH($G$12,$H$12,'01_Parametros'!$B$5,'01_Parametros'!$B$5,"Days=A","Fill=B","Dir=H"),1,2),BDH($G$12,$H$12,'01_Parametros'!$B$5,'01_Parametros'!$B$5,"Days=A","Fill=B")) | L12: =IFERROR(INDEX(BDH($G$12,$H$12,'01_Parametros'!$B$6,'01_Parametros'!$B$6,"Days=A","Fill=B","Dir=H"),1,2),BDH($G$12,$H$12,'01_Parametros'!$B$6,'01_Parametros'!$B$6,"Days=A","Fill=B")) | M12: =IFERROR(INDEX(BDH($G$12,$H$12,'01_Parametros'!$B$7,'01_Parametros'!$B$7,"Days=A","Fill=B","Dir=H"),1,2),BDH($G$12,$H$12,'01_Parametros'!$B$7,'01_Parametros'!$B$7,"Days=A","Fill=B")) | N12: Term SOFR 6M - CME
A13: 12 | B13: money_market | C13: US | D13: TERM_SOFR_12M | E13: 12M | F13: 1 | G13: USOSFR12Z BGN Curncy | H13: PX_LAST | I13: percent | J13: =IFERROR(INDEX(BDH($G$13,$H$13,'01_Parametros'!$B$3,'01_Parametros'!$B$3,"Days=A","Fill=B","Dir=H"),1,2),BDH($G$13,$H$13,'01_Parametros'!$B$3,'01_Parametros'!$B$3,"Days=A","Fill=B")) | K13: =IFERROR(INDEX(BDH($G$13,$H$13,'01_Parametros'!$B$5,'01_Parametros'!$B$5,"Days=A","Fill=B","Dir=H"),1,2),BDH($G$13,$H$13,'01_Parametros'!$B$5,'01_Parametros'!$B$5,"Days=A","Fill=B")) | L13: =IFERROR(INDEX(BDH($G$13,$H$13,'01_Parametros'!$B$6,'01_Parametros'!$B$6,"Days=A","Fill=B","Dir=H"),1,2),BDH($G$13,$H$13,'01_Parametros'!$B$6,'01_Parametros'!$B$6,"Days=A","Fill=B")) | M13: =IFERROR(INDEX(BDH($G$13,$H$13,'01_Parametros'!$B$7,'01_Parametros'!$B$7,"Days=A","Fill=B","Dir=H"),1,2),BDH($G$13,$H$13,'01_Parametros'!$B$7,'01_Parametros'!$B$7,"Days=A","Fill=B")) | N13: Term SOFR 12M - CME
A14: 13 | B14: yield_curve | C14: US | D14: UST | E14: 1M | F14: 0.083 | G14: USGG1M Index | H14: PX_LAST | I14: percent | J14: =IFERROR(INDEX(BDH($G$14,$H$14,'01_Parametros'!$B$3,'01_Parametros'!$B$3,"Days=A","Fill=B","Dir=H"),1,2),BDH($G$14,$H$14,'01_Parametros'!$B$3,'01_Parametros'!$B$3,"Days=A","Fill=B")) | K14: =IFERROR(INDEX(BDH($G$14,$H$14,'01_Parametros'!$B$5,'01_Parametros'!$B$5,"Days=A","Fill=B","Dir=H"),1,2),BDH($G$14,$H$14,'01_Parametros'!$B$5,'01_Parametros'!$B$5,"Days=A","Fill=B")) | L14: =IFERROR(INDEX(BDH($G$14,$H$14,'01_Parametros'!$B$6,'01_Parametros'!$B$6,"Days=A","Fill=B","Dir=H"),1,2),BDH($G$14,$H$14,'01_Parametros'!$B$6,'01_Parametros'!$B$6,"Days=A","Fill=B")) | M14: =IFERROR(INDEX(BDH($G$14,$H$14,'01_Parametros'!$B$7,'01_Parametros'!$B$7,"Days=A","Fill=B","Dir=H"),1,2),BDH($G$14,$H$14,'01_Parametros'!$B$7,'01_Parametros'!$B$7,"Days=A","Fill=B")) | N14: US Treasury 1M nominal
A15: 14 | B15: yield_curve | C15: US | D15: UST | E15: 3M | F15: 0.25 | G15: USGG3M Index | H15: PX_LAST | I15: percent | J15: =IFERROR(INDEX(BDH($G$15,$H$15,'01_Parametros'!$B$3,'01_Parametros'!$B$3,"Days=A","Fill=B","Dir=H"),1,2),BDH($G$15,$H$15,'01_Parametros'!$B$3,'01_Parametros'!$B$3,"Days=A","Fill=B")) | K15: =IFERROR(INDEX(BDH($G$15,$H$15,'01_Parametros'!$B$5,'01_Parametros'!$B$5,"Days=A","Fill=B","Dir=H"),1,2),BDH($G$15,$H$15,'01_Parametros'!$B$5,'01_Parametros'!$B$5,"Days=A","Fill=B")) | L15: =IFERROR(INDEX(BDH($G$15,$H$15,'01_Parametros'!$B$6,'01_Parametros'!$B$6,"Days=A","Fill=B","Dir=H"),1,2),BDH($G$15,$H$15,'01_Parametros'!$B$6,'01_Parametros'!$B$6,"Days=A","Fill=B")) | M15: =IFERROR(INDEX(BDH($G$15,$H$15,'01_Parametros'!$B$7,'01_Parametros'!$B$7,"Days=A","Fill=B","Dir=H"),1,2),BDH($G$15,$H$15,'01_Parametros'!$B$7,'01_Parametros'!$B$7,"Days=A","Fill=B")) | N15: US Treasury 3M nominal
A16: 15 | B16: yield_curve | C16: US | D16: UST | E16: 6M | F16: 0.5 | G16: USGG6M Index | H16: PX_LAST | I16: percent | J16: =IFERROR(INDEX(BDH($G$16,$H$16,'01_Parametros'!$B$3,'01_Parametros'!$B$3,"Days=A","Fill=B","Dir=H"),1,2),BDH($G$16,$H$16,'01_Parametros'!$B$3,'01_Parametros'!$B$3,"Days=A","Fill=B")) | K16: =IFERROR(INDEX(BDH($G$16,$H$16,'01_Parametros'!$B$5,'01_Parametros'!$B$5,"Days=A","Fill=B","Dir=H"),1,2),BDH($G$16,$H$16,'01_Parametros'!$B$5,'01_Parametros'!$B$5,"Days=A","Fill=B")) | L16: =IFERROR(INDEX(BDH($G$16,$H$16,'01_Parametros'!$B$6,'01_Parametros'!$B$6,"Days=A","Fill=B","Dir=H"),1,2),BDH($G$16,$H$16,'01_Parametros'!$B$6,'01_Parametros'!$B$6,"Days=A","Fill=B")) | M16: =IFERROR(INDEX(BDH($G$16,$H$16,'01_Parametros'!$B$7,'01_Parametros'!$B$7,"Days=A","Fill=B","Dir=H"),1,2),BDH($G$16,$H$16,'01_Parametros'!$B$7,'01_Parametros'!$B$7,"Days=A","Fill=B")) | N16: US Treasury 6M nominal
A17: 16 | B17: yield_curve | C17: US | D17: UST | E17: 1Y | F17: 1 | G17: USGG12M Index | H17: PX_LAST | I17: percent | J17: =IFERROR(INDEX(BDH($G$17,$H$17,'01_Parametros'!$B$3,'01_Parametros'!$B$3,"Days=A","Fill=B","Dir=H"),1,2),BDH($G$17,$H$17,'01_Parametros'!$B$3,'01_Parametros'!$B$3,"Days=A","Fill=B")) | K17: =IFERROR(INDEX(BDH($G$17,$H$17,'01_Parametros'!$B$5,'01_Parametros'!$B$5,"Days=A","Fill=B","Dir=H"),1,2),BDH($G$17,$H$17,'01_Parametros'!$B$5,'01_Parametros'!$B$5,"Days=A","Fill=B")) | L17: =IFERROR(INDEX(BDH($G$17,$H$17,'01_Parametros'!$B$6,'01_Parametros'!$B$6,"Days=A","Fill=B","Dir=H"),1,2),BDH($G$17,$H$17,'01_Parametros'!$B$6,'01_Parametros'!$B$6,"Days=A","Fill=B")) | M17: =IFERROR(INDEX(BDH($G$17,$H$17,'01_Parametros'!$B$7,'01_Parametros'!$B$7,"Days=A","Fill=B","Dir=H"),1,2),BDH($G$17,$H$17,'01_Parametros'!$B$7,'01_Parametros'!$B$7,"Days=A","Fill=B")) | N17: US Treasury 1Y nominal
A18: 17 | B18: yield_curve | C18: US | D18: UST | E18: 2Y | F18: 2 | G18: USGG2YR Index | H18: PX_LAST | I18: percent | J18: =IFERROR(INDEX(BDH($G$18,$H$18,'01_Parametros'!$B$3,'01_Parametros'!$B$3,"Days=A","Fill=B","Dir=H"),1,2),BDH($G$18,$H$18,'01_Parametros'!$B$3,'01_Parametros'!$B$3,"Days=A","Fill=B")) | K18: =IFERROR(INDEX(BDH($G$18,$H$18,'01_Parametros'!$B$5,'01_Parametros'!$B$5,"Days=A","Fill=B","Dir=H"),1,2),BDH($G$18,$H$18,'01_Parametros'!$B$5,'01_Parametros'!$B$5,"Days=A","Fill=B")) | L18: =IFERROR(INDEX(BDH($G$18,$H$18,'01_Parametros'!$B$6,'01_Parametros'!$B$6,"Days=A","Fill=B","Dir=H"),1,2),BDH($G$18,$H$18,'01_Parametros'!$B$6,'01_Parametros'!$B$6,"Days=A","Fill=B")) | M18: =IFERROR(INDEX(BDH($G$18,$H$18,'01_Parametros'!$B$7,'01_Parametros'!$B$7,"Days=A","Fill=B","Dir=H"),1,2),BDH($G$18,$H$18,'01_Parametros'!$B$7,'01_Parametros'!$B$7,"Days=A","Fill=B")) | N18: US Treasury 2Y nominal
A19: 18 | B19: yield_curve | C19: US | D19: UST | E19: 3Y | F19: 3 | G19: USGG3YR Index | H19: PX_LAST | I19: percent | J19: =IFERROR(INDEX(BDH($G$19,$H$19,'01_Parametros'!$B$3,'01_Parametros'!$B$3,"Days=A","Fill=B","Dir=H"),1,2),BDH($G$19,$H$19,'01_Parametros'!$B$3,'01_Parametros'!$B$3,"Days=A","Fill=B")) | K19: =IFERROR(INDEX(BDH($G$19,$H$19,'01_Parametros'!$B$5,'01_Parametros'!$B$5,"Days=A","Fill=B","Dir=H"),1,2),BDH($G$19,$H$19,'01_Parametros'!$B$5,'01_Parametros'!$B$5,"Days=A","Fill=B")) | L19: =IFERROR(INDEX(BDH($G$19,$H$19,'01_Parametros'!$B$6,'01_Parametros'!$B$6,"Days=A","Fill=B","Dir=H"),1,2),BDH($G$19,$H$19,'01_Parametros'!$B$6,'01_Parametros'!$B$6,"Days=A","Fill=B")) | M19: =IFERROR(INDEX(BDH($G$19,$H$19,'01_Parametros'!$B$7,'01_Parametros'!$B$7,"Days=A","Fill=B","Dir=H"),1,2),BDH($G$19,$H$19,'01_Parametros'!$B$7,'01_Parametros'!$B$7,"Days=A","Fill=B")) | N19: US Treasury 3Y nominal
A20: 19 | B20: yield_curve | C20: US | D20: UST | E20: 5Y | F20: 5 | G20: USGG5YR Index | H20: PX_LAST | I20: percent | J20: =IFERROR(INDEX(BDH($G$20,$H$20,'01_Parametros'!$B$3,'01_Parametros'!$B$3,"Days=A","Fill=B","Dir=H"),1,2),BDH($G$20,$H$20,'01_Parametros'!$B$3,'01_Parametros'!$B$3,"Days=A","Fill=B")) | K20: =IFERROR(INDEX(BDH($G$20,$H$20,'01_Parametros'!$B$5,'01_Parametros'!$B$5,"Days=A","Fill=B","Dir=H"),1,2),BDH($G$20,$H$20,'01_Parametros'!$B$5,'01_Parametros'!$B$5,"Days=A","Fill=B")) | L20: =IFERROR(INDEX(BDH($G$20,$H$20,'01_Parametros'!$B$6,'01_Parametros'!$B$6,"Days=A","Fill=B","Dir=H"),1,2),BDH($G$20,$H$20,'01_Parametros'!$B$6,'01_Parametros'!$B$6,"Days=A","Fill=B")) | M20: =IFERROR(INDEX(BDH($G$20,$H$20,'01_Parametros'!$B$7,'01_Parametros'!$B$7,"Days=A","Fill=B","Dir=H"),1,2),BDH($G$20,$H$20,'01_Parametros'!$B$7,'01_Parametros'!$B$7,"Days=A","Fill=B")) | N20: US Treasury 5Y nominal
A21: 20 | B21: yield_curve | C21: US | D21: UST | E21: 7Y | F21: 7 | G21: USGG7YR Index | H21: PX_LAST | I21: percent | J21: =IFERROR(INDEX(BDH($G$21,$H$21,'01_Parametros'!$B$3,'01_Parametros'!$B$3,"Days=A","Fill=B","Dir=H"),1,2),BDH($G$21,$H$21,'01_Parametros'!$B$3,'01_Parametros'!$B$3,"Days=A","Fill=B")) | K21: =IFERROR(INDEX(BDH($G$21,$H$21,'01_Parametros'!$B$5,'01_Parametros'!$B$5,"Days=A","Fill=B","Dir=H"),1,2),BDH($G$21,$H$21,'01_Parametros'!$B$5,'01_Parametros'!$B$5,"Days=A","Fill=B")) | L21: =IFERROR(INDEX(BDH($G$21,$H$21,'01_Parametros'!$B$6,'01_Parametros'!$B$6,"Days=A","Fill=B","Dir=H"),1,2),BDH($G$21,$H$21,'01_Parametros'!$B$6,'01_Parametros'!$B$6,"Days=A","Fill=B")) | M21: =IFERROR(INDEX(BDH($G$21,$H$21,'01_Parametros'!$B$7,'01_Parametros'!$B$7,"Days=A","Fill=B","Dir=H"),1,2),BDH($G$21,$H$21,'01_Parametros'!$B$7,'01_Parametros'!$B$7,"Days=A","Fill=B")) | N21: US Treasury 7Y nominal
A22: 21 | B22: yield_curve | C22: US | D22: UST | E22: 10Y | F22: 10 | G22: USGG10YR Index | H22: PX_LAST | I22: percent | J22: =IFERROR(INDEX(BDH($G$22,$H$22,'01_Parametros'!$B$3,'01_Parametros'!$B$3,"Days=A","Fill=B","Dir=H"),1,2),BDH($G$22,$H$22,'01_Parametros'!$B$3,'01_Parametros'!$B$3,"Days=A","Fill=B")) | K22: =IFERROR(INDEX(BDH($G$22,$H$22,'01_Parametros'!$B$5,'01_Parametros'!$B$5,"Days=A","Fill=B","Dir=H"),1,2),BDH($G$22,$H$22,'01_Parametros'!$B$5,'01_Parametros'!$B$5,"Days=A","Fill=B")) | L22: =IFERROR(INDEX(BDH($G$22,$H$22,'01_Parametros'!$B$6,'01_Parametros'!$B$6,"Days=A","Fill=B","Dir=H"),1,2),BDH($G$22,$H$22,'01_Parametros'!$B$6,'01_Parametros'!$B$6,"Days=A","Fill=B")) | M22: =IFERROR(INDEX(BDH($G$22,$H$22,'01_Parametros'!$B$7,'01_Parametros'!$B$7,"Days=A","Fill=B","Dir=H"),1,2),BDH($G$22,$H$22,'01_Parametros'!$B$7,'01_Parametros'!$B$7,"Days=A","Fill=B")) | N22: US Treasury 10Y nominal
A23: 22 | B23: yield_curve | C23: US | D23: UST | E23: 20Y | F23: 20 | G23: USGG20YR Index | H23: PX_LAST | I23: percent | J23: =IFERROR(INDEX(BDH($G$23,$H$23,'01_Parametros'!$B$3,'01_Parametros'!$B$3,"Days=A","Fill=B","Dir=H"),1,2),BDH($G$23,$H$23,'01_Parametros'!$B$3,'01_Parametros'!$B$3,"Days=A","Fill=B")) | K23: =IFERROR(INDEX(BDH($G$23,$H$23,'01_Parametros'!$B$5,'01_Parametros'!$B$5,"Days=A","Fill=B","Dir=H"),1,2),BDH($G$23,$H$23,'01_Parametros'!$B$5,'01_Parametros'!$B$5,"Days=A","Fill=B")) | L23: =IFERROR(INDEX(BDH($G$23,$H$23,'01_Parametros'!$B$6,'01_Parametros'!$B$6,"Days=A","Fill=B","Dir=H"),1,2),BDH($G$23,$H$23,'01_Parametros'!$B$6,'01_Parametros'!$B$6,"Days=A","Fill=B")) | M23: =IFERROR(INDEX(BDH($G$23,$H$23,'01_Parametros'!$B$7,'01_Parametros'!$B$7,"Days=A","Fill=B","Dir=H"),1,2),BDH($G$23,$H$23,'01_Parametros'!$B$7,'01_Parametros'!$B$7,"Days=A","Fill=B")) | N23: US Treasury 20Y nominal
A24: 23 | B24: yield_curve | C24: US | D24: UST | E24: 30Y | F24: 30 | G24: USGG30YR Index | H24: PX_LAST | I24: percent | J24: =IFERROR(INDEX(BDH($G$24,$H$24,'01_Parametros'!$B$3,'01_Parametros'!$B$3,"Days=A","Fill=B","Dir=H"),1,2),BDH($G$24,$H$24,'01_Parametros'!$B$3,'01_Parametros'!$B$3,"Days=A","Fill=B")) | K24: =IFERROR(INDEX(BDH($G$24,$H$24,'01_Parametros'!$B$5,'01_Parametros'!$B$5,"Days=A","Fill=B","Dir=H"),1,2),BDH($G$24,$H$24,'01_Parametros'!$B$5,'01_Parametros'!$B$5,"Days=A","Fill=B")) | L24: =IFERROR(INDEX(BDH($G$24,$H$24,'01_Parametros'!$B$6,'01_Parametros'!$B$6,"Days=A","Fill=B","Dir=H"),1,2),BDH($G$24,$H$24,'01_Parametros'!$B$6,'01_Parametros'!$B$6,"Days=A","Fill=B")) | M24: =IFERROR(INDEX(BDH($G$24,$H$24,'01_Parametros'!$B$7,'01_Parametros'!$B$7,"Days=A","Fill=B","Dir=H"),1,2),BDH($G$24,$H$24,'01_Parametros'!$B$7,'01_Parametros'!$B$7,"Days=A","Fill=B")) | N24: US Treasury 30Y nominal
A25: 24 | B25: real_curve | C25: US | D25: TIPS | E25: 5Y | F25: 5 | G25: USGGT05Y Index | H25: PX_LAST | I25: percent | J25: =IFERROR(INDEX(BDH($G$25,$H$25,'01_Parametros'!$B$3,'01_Parametros'!$B$3,"Days=A","Fill=B","Dir=H"),1,2),BDH($G$25,$H$25,'01_Parametros'!$B$3,'01_Parametros'!$B$3,"Days=A","Fill=B")) | K25: =IFERROR(INDEX(BDH($G$25,$H$25,'01_Parametros'!$B$5,'01_Parametros'!$B$5,"Days=A","Fill=B","Dir=H"),1,2),BDH($G$25,$H$25,'01_Parametros'!$B$5,'01_Parametros'!$B$5,"Days=A","Fill=B")) | L25: =IFERROR(INDEX(BDH($G$25,$H$25,'01_Parametros'!$B$6,'01_Parametros'!$B$6,"Days=A","Fill=B","Dir=H"),1,2),BDH($G$25,$H$25,'01_Parametros'!$B$6,'01_Parametros'!$B$6,"Days=A","Fill=B")) | M25: =IFERROR(INDEX(BDH($G$25,$H$25,'01_Parametros'!$B$7,'01_Parametros'!$B$7,"Days=A","Fill=B","Dir=H"),1,2),BDH($G$25,$H$25,'01_Parametros'!$B$7,'01_Parametros'!$B$7,"Days=A","Fill=B")) | N25: US TIPS 5Y real yield CMT - confirmar ticker
A26: 25 | B26: real_curve | C26: US | D26: TIPS | E26: 10Y | F26: 10 | G26: USGGT10Y Index | H26: PX_LAST | I26: percent | J26: =IFERROR(INDEX(BDH($G$26,$H$26,'01_Parametros'!$B$3,'01_Parametros'!$B$3,"Days=A","Fill=B","Dir=H"),1,2),BDH($G$26,$H$26,'01_Parametros'!$B$3,'01_Parametros'!$B$3,"Days=A","Fill=B")) | K26: =IFERROR(INDEX(BDH($G$26,$H$26,'01_Parametros'!$B$5,'01_Parametros'!$B$5,"Days=A","Fill=B","Dir=H"),1,2),BDH($G$26,$H$26,'01_Parametros'!$B$5,'01_Parametros'!$B$5,"Days=A","Fill=B")) | L26: =IFERROR(INDEX(BDH($G$26,$H$26,'01_Parametros'!$B$6,'01_Parametros'!$B$6,"Days=A","Fill=B","Dir=H"),1,2),BDH($G$26,$H$26,'01_Parametros'!$B$6,'01_Parametros'!$B$6,"Days=A","Fill=B")) | M26: =IFERROR(INDEX(BDH($G$26,$H$26,'01_Parametros'!$B$7,'01_Parametros'!$B$7,"Days=A","Fill=B","Dir=H"),1,2),BDH($G$26,$H$26,'01_Parametros'!$B$7,'01_Parametros'!$B$7,"Days=A","Fill=B")) | N26: US TIPS 10Y real yield CMT - confirmar ticker
A27: 26 | B27: real_curve | C27: US | D27: TIPS | E27: 20Y | F27: 20 | G27: USGGT20Y Index | H27: PX_LAST | I27: percent | J27: =IFERROR(INDEX(BDH($G$27,$H$27,'01_Parametros'!$B$3,'01_Parametros'!$B$3,"Days=A","Fill=B","Dir=H"),1,2),BDH($G$27,$H$27,'01_Parametros'!$B$3,'01_Parametros'!$B$3,"Days=A","Fill=B")) | K27: =IFERROR(INDEX(BDH($G$27,$H$27,'01_Parametros'!$B$5,'01_Parametros'!$B$5,"Days=A","Fill=B","Dir=H"),1,2),BDH($G$27,$H$27,'01_Parametros'!$B$5,'01_Parametros'!$B$5,"Days=A","Fill=B")) | L27: =IFERROR(INDEX(BDH($G$27,$H$27,'01_Parametros'!$B$6,'01_Parametros'!$B$6,"Days=A","Fill=B","Dir=H"),1,2),BDH($G$27,$H$27,'01_Parametros'!$B$6,'01_Parametros'!$B$6,"Days=A","Fill=B")) | M27: =IFERROR(INDEX(BDH($G$27,$H$27,'01_Parametros'!$B$7,'01_Parametros'!$B$7,"Days=A","Fill=B","Dir=H"),1,2),BDH($G$27,$H$27,'01_Parametros'!$B$7,'01_Parametros'!$B$7,"Days=A","Fill=B")) | N27: US TIPS 20Y real yield CMT - confirmar ticker
A28: 27 | B28: real_curve | C28: US | D28: TIPS | E28: 30Y | F28: 30 | G28: USGGT30Y Index | H28: PX_LAST | I28: percent | J28: =IFERROR(INDEX(BDH($G$28,$H$28,'01_Parametros'!$B$3,'01_Parametros'!$B$3,"Days=A","Fill=B","Dir=H"),1,2),BDH($G$28,$H$28,'01_Parametros'!$B$3,'01_Parametros'!$B$3,"Days=A","Fill=B")) | K28: =IFERROR(INDEX(BDH($G$28,$H$28,'01_Parametros'!$B$5,'01_Parametros'!$B$5,"Days=A","Fill=B","Dir=H"),1,2),BDH($G$28,$H$28,'01_Parametros'!$B$5,'01_Parametros'!$B$5,"Days=A","Fill=B")) | L28: =IFERROR(INDEX(BDH($G$28,$H$28,'01_Parametros'!$B$6,'01_Parametros'!$B$6,"Days=A","Fill=B","Dir=H"),1,2),BDH($G$28,$H$28,'01_Parametros'!$B$6,'01_Parametros'!$B$6,"Days=A","Fill=B")) | M28: =IFERROR(INDEX(BDH($G$28,$H$28,'01_Parametros'!$B$7,'01_Parametros'!$B$7,"Days=A","Fill=B","Dir=H"),1,2),BDH($G$28,$H$28,'01_Parametros'!$B$7,'01_Parametros'!$B$7,"Days=A","Fill=B")) | N28: US TIPS 30Y real yield CMT - confirmar ticker
A29: 28 | B29: breakeven | C29: US | D29: BE_INFL | E29: 2Y | F29: 2 | G29: USGGBE02 Index | H29: PX_LAST | I29: percent | J29: =IFERROR(INDEX(BDH($G$29,$H$29,'01_Parametros'!$B$3,'01_Parametros'!$B$3,"Days=A","Fill=B","Dir=H"),1,2),BDH($G$29,$H$29,'01_Parametros'!$B$3,'01_Parametros'!$B$3,"Days=A","Fill=B")) | K29: =IFERROR(INDEX(BDH($G$29,$H$29,'01_Parametros'!$B$5,'01_Parametros'!$B$5,"Days=A","Fill=B","Dir=H"),1,2),BDH($G$29,$H$29,'01_Parametros'!$B$5,'01_Parametros'!$B$5,"Days=A","Fill=B")) | L29: =IFERROR(INDEX(BDH($G$29,$H$29,'01_Parametros'!$B$6,'01_Parametros'!$B$6,"Days=A","Fill=B","Dir=H"),1,2),BDH($G$29,$H$29,'01_Parametros'!$B$6,'01_Parametros'!$B$6,"Days=A","Fill=B")) | M29: =IFERROR(INDEX(BDH($G$29,$H$29,'01_Parametros'!$B$7,'01_Parametros'!$B$7,"Days=A","Fill=B","Dir=H"),1,2),BDH($G$29,$H$29,'01_Parametros'!$B$7,'01_Parametros'!$B$7,"Days=A","Fill=B")) | N29: US 2Y breakeven inflation
A30: 29 | B30: breakeven | C30: US | D30: BE_INFL | E30: 5Y | F30: 5 | G30: USGGBE05 Index | H30: PX_LAST | I30: percent | J30: =IFERROR(INDEX(BDH($G$30,$H$30,'01_Parametros'!$B$3,'01_Parametros'!$B$3,"Days=A","Fill=B","Dir=H"),1,2),BDH($G$30,$H$30,'01_Parametros'!$B$3,'01_Parametros'!$B$3,"Days=A","Fill=B")) | K30: =IFERROR(INDEX(BDH($G$30,$H$30,'01_Parametros'!$B$5,'01_Parametros'!$B$5,"Days=A","Fill=B","Dir=H"),1,2),BDH($G$30,$H$30,'01_Parametros'!$B$5,'01_Parametros'!$B$5,"Days=A","Fill=B")) | L30: =IFERROR(INDEX(BDH($G$30,$H$30,'01_Parametros'!$B$6,'01_Parametros'!$B$6,"Days=A","Fill=B","Dir=H"),1,2),BDH($G$30,$H$30,'01_Parametros'!$B$6,'01_Parametros'!$B$6,"Days=A","Fill=B")) | M30: =IFERROR(INDEX(BDH($G$30,$H$30,'01_Parametros'!$B$7,'01_Parametros'!$B$7,"Days=A","Fill=B","Dir=H"),1,2),BDH($G$30,$H$30,'01_Parametros'!$B$7,'01_Parametros'!$B$7,"Days=A","Fill=B")) | N30: US 5Y breakeven inflation
A31: 30 | B31: breakeven | C31: US | D31: BE_INFL | E31: 10Y | F31: 10 | G31: USGGBE10 Index | H31: PX_LAST | I31: percent | J31: =IFERROR(INDEX(BDH($G$31,$H$31,'01_Parametros'!$B$3,'01_Parametros'!$B$3,"Days=A","Fill=B","Dir=H"),1,2),BDH($G$31,$H$31,'01_Parametros'!$B$3,'01_Parametros'!$B$3,"Days=A","Fill=B")) | K31: =IFERROR(INDEX(BDH($G$31,$H$31,'01_Parametros'!$B$5,'01_Parametros'!$B$5,"Days=A","Fill=B","Dir=H"),1,2),BDH($G$31,$H$31,'01_Parametros'!$B$5,'01_Parametros'!$B$5,"Days=A","Fill=B")) | L31: =IFERROR(INDEX(BDH($G$31,$H$31,'01_Parametros'!$B$6,'01_Parametros'!$B$6,"Days=A","Fill=B","Dir=H"),1,2),BDH($G$31,$H$31,'01_Parametros'!$B$6,'01_Parametros'!$B$6,"Days=A","Fill=B")) | M31: =IFERROR(INDEX(BDH($G$31,$H$31,'01_Parametros'!$B$7,'01_Parametros'!$B$7,"Days=A","Fill=B","Dir=H"),1,2),BDH($G$31,$H$31,'01_Parametros'!$B$7,'01_Parametros'!$B$7,"Days=A","Fill=B")) | N31: US 10Y breakeven inflation
A32: 31 | B32: breakeven | C32: US | D32: BE_INFL | E32: 30Y | F32: 30 | G32: USGGBE30 Index | H32: PX_LAST | I32: percent | J32: =IFERROR(INDEX(BDH($G$32,$H$32,'01_Parametros'!$B$3,'01_Parametros'!$B$3,"Days=A","Fill=B","Dir=H"),1,2),BDH($G$32,$H$32,'01_Parametros'!$B$3,'01_Parametros'!$B$3,"Days=A","Fill=B")) | K32: =IFERROR(INDEX(BDH($G$32,$H$32,'01_Parametros'!$B$5,'01_Parametros'!$B$5,"Days=A","Fill=B","Dir=H"),1,2),BDH($G$32,$H$32,'01_Parametros'!$B$5,'01_Parametros'!$B$5,"Days=A","Fill=B")) | L32: =IFERROR(INDEX(BDH($G$32,$H$32,'01_Parametros'!$B$6,'01_Parametros'!$B$6,"Days=A","Fill=B","Dir=H"),1,2),BDH($G$32,$H$32,'01_Parametros'!$B$6,'01_Parametros'!$B$6,"Days=A","Fill=B")) | M32: =IFERROR(INDEX(BDH($G$32,$H$32,'01_Parametros'!$B$7,'01_Parametros'!$B$7,"Days=A","Fill=B","Dir=H"),1,2),BDH($G$32,$H$32,'01_Parametros'!$B$7,'01_Parametros'!$B$7,"Days=A","Fill=B")) | N32: US 30Y breakeven inflation
A33: 32 | B33: swap_curve | C33: US | D33: SOFR_OIS | E33: 2Y | F33: 2 | G33: USOSFR2 BGN Curncy | H33: PX_LAST | I33: percent | J33: =IFERROR(INDEX(BDH($G$33,$H$33,'01_Parametros'!$B$3,'01_Parametros'!$B$3,"Days=A","Fill=B","Dir=H"),1,2),BDH($G$33,$H$33,'01_Parametros'!$B$3,'01_Parametros'!$B$3,"Days=A","Fill=B")) | K33: =IFERROR(INDEX(BDH($G$33,$H$33,'01_Parametros'!$B$5,'01_Parametros'!$B$5,"Days=A","Fill=B","Dir=H"),1,2),BDH($G$33,$H$33,'01_Parametros'!$B$5,'01_Parametros'!$B$5,"Days=A","Fill=B")) | L33: =IFERROR(INDEX(BDH($G$33,$H$33,'01_Parametros'!$B$6,'01_Parametros'!$B$6,"Days=A","Fill=B","Dir=H"),1,2),BDH($G$33,$H$33,'01_Parametros'!$B$6,'01_Parametros'!$B$6,"Days=A","Fill=B")) | M33: =IFERROR(INDEX(BDH($G$33,$H$33,'01_Parametros'!$B$7,'01_Parametros'!$B$7,"Days=A","Fill=B","Dir=H"),1,2),BDH($G$33,$H$33,'01_Parametros'!$B$7,'01_Parametros'!$B$7,"Days=A","Fill=B")) | N33: USD SOFR OIS 2Y - confirmar convencion
A34: 33 | B34: swap_curve | C34: US | D34: SOFR_OIS | E34: 5Y | F34: 5 | G34: USOSFR5 BGN Curncy | H34: PX_LAST | I34: percent | J34: =IFERROR(INDEX(BDH($G$34,$H$34,'01_Parametros'!$B$3,'01_Parametros'!$B$3,"Days=A","Fill=B","Dir=H"),1,2),BDH($G$34,$H$34,'01_Parametros'!$B$3,'01_Parametros'!$B$3,"Days=A","Fill=B")) | K34: =IFERROR(INDEX(BDH($G$34,$H$34,'01_Parametros'!$B$5,'01_Parametros'!$B$5,"Days=A","Fill=B","Dir=H"),1,2),BDH($G$34,$H$34,'01_Parametros'!$B$5,'01_Parametros'!$B$5,"Days=A","Fill=B")) | L34: =IFERROR(INDEX(BDH($G$34,$H$34,'01_Parametros'!$B$6,'01_Parametros'!$B$6,"Days=A","Fill=B","Dir=H"),1,2),BDH($G$34,$H$34,'01_Parametros'!$B$6,'01_Parametros'!$B$6,"Days=A","Fill=B")) | M34: =IFERROR(INDEX(BDH($G$34,$H$34,'01_Parametros'!$B$7,'01_Parametros'!$B$7,"Days=A","Fill=B","Dir=H"),1,2),BDH($G$34,$H$34,'01_Parametros'!$B$7,'01_Parametros'!$B$7,"Days=A","Fill=B")) | N34: USD SOFR OIS 5Y - confirmar convencion
A35: 34 | B35: swap_curve | C35: US | D35: SOFR_OIS | E35: 10Y | F35: 10 | G35: USOSFR10 BGN Curncy | H35: PX_LAST | I35: percent | J35: =IFERROR(INDEX(BDH($G$35,$H$35,'01_Parametros'!$B$3,'01_Parametros'!$B$3,"Days=A","Fill=B","Dir=H"),1,2),BDH($G$35,$H$35,'01_Parametros'!$B$3,'01_Parametros'!$B$3,"Days=A","Fill=B")) | K35: =IFERROR(INDEX(BDH($G$35,$H$35,'01_Parametros'!$B$5,'01_Parametros'!$B$5,"Days=A","Fill=B","Dir=H"),1,2),BDH($G$35,$H$35,'01_Parametros'!$B$5,'01_Parametros'!$B$5,"Days=A","Fill=B")) | L35: =IFERROR(INDEX(BDH($G$35,$H$35,'01_Parametros'!$B$6,'01_Parametros'!$B$6,"Days=A","Fill=B","Dir=H"),1,2),BDH($G$35,$H$35,'01_Parametros'!$B$6,'01_Parametros'!$B$6,"Days=A","Fill=B")) | M35: =IFERROR(INDEX(BDH($G$35,$H$35,'01_Parametros'!$B$7,'01_Parametros'!$B$7,"Days=A","Fill=B","Dir=H"),1,2),BDH($G$35,$H$35,'01_Parametros'!$B$7,'01_Parametros'!$B$7,"Days=A","Fill=B")) | N35: USD SOFR OIS 10Y - confirmar convencion
A36: 35 | B36: swap_curve | C36: US | D36: SOFR_OIS | E36: 30Y | F36: 30 | G36: USOSFR30 BGN Curncy | H36: PX_LAST | I36: percent | J36: =IFERROR(INDEX(BDH($G$36,$H$36,'01_Parametros'!$B$3,'01_Parametros'!$B$3,"Days=A","Fill=B","Dir=H"),1,2),BDH($G$36,$H$36,'01_Parametros'!$B$3,'01_Parametros'!$B$3,"Days=A","Fill=B")) | K36: =IFERROR(INDEX(BDH($G$36,$H$36,'01_Parametros'!$B$5,'01_Parametros'!$B$5,"Days=A","Fill=B","Dir=H"),1,2),BDH($G$36,$H$36,'01_Parametros'!$B$5,'01_Parametros'!$B$5,"Days=A","Fill=B")) | L36: =IFERROR(INDEX(BDH($G$36,$H$36,'01_Parametros'!$B$6,'01_Parametros'!$B$6,"Days=A","Fill=B","Dir=H"),1,2),BDH($G$36,$H$36,'01_Parametros'!$B$6,'01_Parametros'!$B$6,"Days=A","Fill=B")) | M36: =IFERROR(INDEX(BDH($G$36,$H$36,'01_Parametros'!$B$7,'01_Parametros'!$B$7,"Days=A","Fill=B","Dir=H"),1,2),BDH($G$36,$H$36,'01_Parametros'!$B$7,'01_Parametros'!$B$7,"Days=A","Fill=B")) | N36: USD SOFR OIS 30Y - confirmar convencion
A37: 36 | B37: policy | C37: EU | D37: ECB_DFR | E37: — | F37: 0 | G37: EURR002W Index | H37: PX_LAST | I37: percent | J37: =IFERROR(INDEX(BDH($G$37,$H$37,'01_Parametros'!$B$3,'01_Parametros'!$B$3,"Days=A","Fill=B","Dir=H"),1,2),BDH($G$37,$H$37,'01_Parametros'!$B$3,'01_Parametros'!$B$3,"Days=A","Fill=B")) | K37: =IFERROR(INDEX(BDH($G$37,$H$37,'01_Parametros'!$B$5,'01_Parametros'!$B$5,"Days=A","Fill=B","Dir=H"),1,2),BDH($G$37,$H$37,'01_Parametros'!$B$5,'01_Parametros'!$B$5,"Days=A","Fill=B")) | L37: =IFERROR(INDEX(BDH($G$37,$H$37,'01_Parametros'!$B$6,'01_Parametros'!$B$6,"Days=A","Fill=B","Dir=H"),1,2),BDH($G$37,$H$37,'01_Parametros'!$B$6,'01_Parametros'!$B$6,"Days=A","Fill=B")) | M37: =IFERROR(INDEX(BDH($G$37,$H$37,'01_Parametros'!$B$7,'01_Parametros'!$B$7,"Days=A","Fill=B","Dir=H"),1,2),BDH($G$37,$H$37,'01_Parametros'!$B$7,'01_Parametros'!$B$7,"Days=A","Fill=B")) | N37: ECB Deposit Facility Rate
A38: 37 | B38: policy | C38: EU | D38: ECB_MRO | E38: — | F38: 0 | G38: EURMR1WI Index | H38: PX_LAST | I38: percent | J38: =IFERROR(INDEX(BDH($G$38,$H$38,'01_Parametros'!$B$3,'01_Parametros'!$B$3,"Days=A","Fill=B","Dir=H"),1,2),BDH($G$38,$H$38,'01_Parametros'!$B$3,'01_Parametros'!$B$3,"Days=A","Fill=B")) | K38: =IFERROR(INDEX(BDH($G$38,$H$38,'01_Parametros'!$B$5,'01_Parametros'!$B$5,"Days=A","Fill=B","Dir=H"),1,2),BDH($G$38,$H$38,'01_Parametros'!$B$5,'01_Parametros'!$B$5,"Days=A","Fill=B")) | L38: =IFERROR(INDEX(BDH($G$38,$H$38,'01_Parametros'!$B$6,'01_Parametros'!$B$6,"Days=A","Fill=B","Dir=H"),1,2),BDH($G$38,$H$38,'01_Parametros'!$B$6,'01_Parametros'!$B$6,"Days=A","Fill=B")) | M38: =IFERROR(INDEX(BDH($G$38,$H$38,'01_Parametros'!$B$7,'01_Parametros'!$B$7,"Days=A","Fill=B","Dir=H"),1,2),BDH($G$38,$H$38,'01_Parametros'!$B$7,'01_Parametros'!$B$7,"Days=A","Fill=B")) | N38: ECB Main Refi Operations — confirmar ticker
A39: 38 | B39: policy | C39: GB | D39: BOE_BANK_RATE | E39: — | F39: 0 | G39: UKBRBASE Index | H39: PX_LAST | I39: percent | J39: =IFERROR(INDEX(BDH($G$39,$H$39,'01_Parametros'!$B$3,'01_Parametros'!$B$3,"Days=A","Fill=B","Dir=H"),1,2),BDH($G$39,$H$39,'01_Parametros'!$B$3,'01_Parametros'!$B$3,"Days=A","Fill=B")) | K39: =IFERROR(INDEX(BDH($G$39,$H$39,'01_Parametros'!$B$5,'01_Parametros'!$B$5,"Days=A","Fill=B","Dir=H"),1,2),BDH($G$39,$H$39,'01_Parametros'!$B$5,'01_Parametros'!$B$5,"Days=A","Fill=B")) | L39: =IFERROR(INDEX(BDH($G$39,$H$39,'01_Parametros'!$B$6,'01_Parametros'!$B$6,"Days=A","Fill=B","Dir=H"),1,2),BDH($G$39,$H$39,'01_Parametros'!$B$6,'01_Parametros'!$B$6,"Days=A","Fill=B")) | M39: =IFERROR(INDEX(BDH($G$39,$H$39,'01_Parametros'!$B$7,'01_Parametros'!$B$7,"Days=A","Fill=B","Dir=H"),1,2),BDH($G$39,$H$39,'01_Parametros'!$B$7,'01_Parametros'!$B$7,"Days=A","Fill=B")) | N39: BoE Bank Rate
A40: 39 | B40: policy | C40: JP | D40: BOJ_POLICY | E40: — | F40: 0 | G40: BOJDPBAL Index | H40: PX_LAST | I40: percent | J40: =IFERROR(INDEX(BDH($G$40,$H$40,'01_Parametros'!$B$3,'01_Parametros'!$B$3,"Days=A","Fill=B","Dir=H"),1,2),BDH($G$40,$H$40,'01_Parametros'!$B$3,'01_Parametros'!$B$3,"Days=A","Fill=B")) | K40: =IFERROR(INDEX(BDH($G$40,$H$40,'01_Parametros'!$B$5,'01_Parametros'!$B$5,"Days=A","Fill=B","Dir=H"),1,2),BDH($G$40,$H$40,'01_Parametros'!$B$5,'01_Parametros'!$B$5,"Days=A","Fill=B")) | L40: =IFERROR(INDEX(BDH($G$40,$H$40,'01_Parametros'!$B$6,'01_Parametros'!$B$6,"Days=A","Fill=B","Dir=H"),1,2),BDH($G$40,$H$40,'01_Parametros'!$B$6,'01_Parametros'!$B$6,"Days=A","Fill=B")) | M40: =IFERROR(INDEX(BDH($G$40,$H$40,'01_Parametros'!$B$7,'01_Parametros'!$B$7,"Days=A","Fill=B","Dir=H"),1,2),BDH($G$40,$H$40,'01_Parametros'!$B$7,'01_Parametros'!$B$7,"Days=A","Fill=B")) | N40: BoJ policy rate
A41: 40 | B41: policy | C41: CN | D41: PBOC_7D_RR | E41: — | F41: 0 | G41: CHRR7TR Index | H41: PX_LAST | I41: percent | J41: =IFERROR(INDEX(BDH($G$41,$H$41,'01_Parametros'!$B$3,'01_Parametros'!$B$3,"Days=A","Fill=B","Dir=H"),1,2),BDH($G$41,$H$41,'01_Parametros'!$B$3,'01_Parametros'!$B$3,"Days=A","Fill=B")) | K41: =IFERROR(INDEX(BDH($G$41,$H$41,'01_Parametros'!$B$5,'01_Parametros'!$B$5,"Days=A","Fill=B","Dir=H"),1,2),BDH($G$41,$H$41,'01_Parametros'!$B$5,'01_Parametros'!$B$5,"Days=A","Fill=B")) | L41: =IFERROR(INDEX(BDH($G$41,$H$41,'01_Parametros'!$B$6,'01_Parametros'!$B$6,"Days=A","Fill=B","Dir=H"),1,2),BDH($G$41,$H$41,'01_Parametros'!$B$6,'01_Parametros'!$B$6,"Days=A","Fill=B")) | M41: =IFERROR(INDEX(BDH($G$41,$H$41,'01_Parametros'!$B$7,'01_Parametros'!$B$7,"Days=A","Fill=B","Dir=H"),1,2),BDH($G$41,$H$41,'01_Parametros'!$B$7,'01_Parametros'!$B$7,"Days=A","Fill=B")) | N41: PBoC 7-day reverse repo — confirmar
A42: 41 | B42: policy | C42: BR | D42: SELIC_META | E42: — | F42: 0 | G42: BZSTSETA Index | H42: PX_LAST | I42: percent | J42: =IFERROR(INDEX(BDH($G$42,$H$42,'01_Parametros'!$B$3,'01_Parametros'!$B$3,"Days=A","Fill=B","Dir=H"),1,2),BDH($G$42,$H$42,'01_Parametros'!$B$3,'01_Parametros'!$B$3,"Days=A","Fill=B")) | K42: =IFERROR(INDEX(BDH($G$42,$H$42,'01_Parametros'!$B$5,'01_Parametros'!$B$5,"Days=A","Fill=B","Dir=H"),1,2),BDH($G$42,$H$42,'01_Parametros'!$B$5,'01_Parametros'!$B$5,"Days=A","Fill=B")) | L42: =IFERROR(INDEX(BDH($G$42,$H$42,'01_Parametros'!$B$6,'01_Parametros'!$B$6,"Days=A","Fill=B","Dir=H"),1,2),BDH($G$42,$H$42,'01_Parametros'!$B$6,'01_Parametros'!$B$6,"Days=A","Fill=B")) | M42: =IFERROR(INDEX(BDH($G$42,$H$42,'01_Parametros'!$B$7,'01_Parametros'!$B$7,"Days=A","Fill=B","Dir=H"),1,2),BDH($G$42,$H$42,'01_Parametros'!$B$7,'01_Parametros'!$B$7,"Days=A","Fill=B")) | N42: Selic target
A43: 42 | B43: policy | C43: MX | D43: BANXICO_TASA | E43: — | F43: 0 | G43: MXONBR Index | H43: PX_LAST | I43: percent | J43: =IFERROR(INDEX(BDH($G$43,$H$43,'01_Parametros'!$B$3,'01_Parametros'!$B$3,"Days=A","Fill=B","Dir=H"),1,2),BDH($G$43,$H$43,'01_Parametros'!$B$3,'01_Parametros'!$B$3,"Days=A","Fill=B")) | K43: =IFERROR(INDEX(BDH($G$43,$H$43,'01_Parametros'!$B$5,'01_Parametros'!$B$5,"Days=A","Fill=B","Dir=H"),1,2),BDH($G$43,$H$43,'01_Parametros'!$B$5,'01_Parametros'!$B$5,"Days=A","Fill=B")) | L43: =IFERROR(INDEX(BDH($G$43,$H$43,'01_Parametros'!$B$6,'01_Parametros'!$B$6,"Days=A","Fill=B","Dir=H"),1,2),BDH($G$43,$H$43,'01_Parametros'!$B$6,'01_Parametros'!$B$6,"Days=A","Fill=B")) | M43: =IFERROR(INDEX(BDH($G$43,$H$43,'01_Parametros'!$B$7,'01_Parametros'!$B$7,"Days=A","Fill=B","Dir=H"),1,2),BDH($G$43,$H$43,'01_Parametros'!$B$7,'01_Parametros'!$B$7,"Days=A","Fill=B")) | N43: Banxico target
A44: 43 | B44: policy | C44: CO | D44: BANREP_TASA | E44: — | F44: 0 | G44: COBR Index | H44: PX_LAST | I44: percent | J44: =IFERROR(INDEX(BDH($G$44,$H$44,'01_Parametros'!$B$3,'01_Parametros'!$B$3,"Days=A","Fill=B","Dir=H"),1,2),BDH($G$44,$H$44,'01_Parametros'!$B$3,'01_Parametros'!$B$3,"Days=A","Fill=B")) | K44: =IFERROR(INDEX(BDH($G$44,$H$44,'01_Parametros'!$B$5,'01_Parametros'!$B$5,"Days=A","Fill=B","Dir=H"),1,2),BDH($G$44,$H$44,'01_Parametros'!$B$5,'01_Parametros'!$B$5,"Days=A","Fill=B")) | L44: =IFERROR(INDEX(BDH($G$44,$H$44,'01_Parametros'!$B$6,'01_Parametros'!$B$6,"Days=A","Fill=B","Dir=H"),1,2),BDH($G$44,$H$44,'01_Parametros'!$B$6,'01_Parametros'!$B$6,"Days=A","Fill=B")) | M44: =IFERROR(INDEX(BDH($G$44,$H$44,'01_Parametros'!$B$7,'01_Parametros'!$B$7,"Days=A","Fill=B","Dir=H"),1,2),BDH($G$44,$H$44,'01_Parametros'!$B$7,'01_Parametros'!$B$7,"Days=A","Fill=B")) | N44: BanRep target
A45: 44 | B45: yield_curve | C45: DE | D45: BUND | E45: 10Y | F45: 10 | G45: GDBR10 Index | H45: PX_LAST | I45: percent | J45: =IFERROR(INDEX(BDH($G$45,$H$45,'01_Parametros'!$B$3,'01_Parametros'!$B$3,"Days=A","Fill=B","Dir=H"),1,2),BDH($G$45,$H$45,'01_Parametros'!$B$3,'01_Parametros'!$B$3,"Days=A","Fill=B")) | K45: =IFERROR(INDEX(BDH($G$45,$H$45,'01_Parametros'!$B$5,'01_Parametros'!$B$5,"Days=A","Fill=B","Dir=H"),1,2),BDH($G$45,$H$45,'01_Parametros'!$B$5,'01_Parametros'!$B$5,"Days=A","Fill=B")) | L45: =IFERROR(INDEX(BDH($G$45,$H$45,'01_Parametros'!$B$6,'01_Parametros'!$B$6,"Days=A","Fill=B","Dir=H"),1,2),BDH($G$45,$H$45,'01_Parametros'!$B$6,'01_Parametros'!$B$6,"Days=A","Fill=B")) | M45: =IFERROR(INDEX(BDH($G$45,$H$45,'01_Parametros'!$B$7,'01_Parametros'!$B$7,"Days=A","Fill=B","Dir=H"),1,2),BDH($G$45,$H$45,'01_Parametros'!$B$7,'01_Parametros'!$B$7,"Days=A","Fill=B")) | N45: Germany Bund 10Y
A46: 45 | B46: yield_curve | C46: GB | D46: GILT | E46: 10Y | F46: 10 | G46: GUKG10 Index | H46: PX_LAST | I46: percent | J46: =IFERROR(INDEX(BDH($G$46,$H$46,'01_Parametros'!$B$3,'01_Parametros'!$B$3,"Days=A","Fill=B","Dir=H"),1,2),BDH($G$46,$H$46,'01_Parametros'!$B$3,'01_Parametros'!$B$3,"Days=A","Fill=B")) | K46: =IFERROR(INDEX(BDH($G$46,$H$46,'01_Parametros'!$B$5,'01_Parametros'!$B$5,"Days=A","Fill=B","Dir=H"),1,2),BDH($G$46,$H$46,'01_Parametros'!$B$5,'01_Parametros'!$B$5,"Days=A","Fill=B")) | L46: =IFERROR(INDEX(BDH($G$46,$H$46,'01_Parametros'!$B$6,'01_Parametros'!$B$6,"Days=A","Fill=B","Dir=H"),1,2),BDH($G$46,$H$46,'01_Parametros'!$B$6,'01_Parametros'!$B$6,"Days=A","Fill=B")) | M46: =IFERROR(INDEX(BDH($G$46,$H$46,'01_Parametros'!$B$7,'01_Parametros'!$B$7,"Days=A","Fill=B","Dir=H"),1,2),BDH($G$46,$H$46,'01_Parametros'!$B$7,'01_Parametros'!$B$7,"Days=A","Fill=B")) | N46: UK Gilt 10Y
A47: 46 | B47: yield_curve | C47: JP | D47: JGB | E47: 10Y | F47: 10 | G47: GJGB10 Index | H47: PX_LAST | I47: percent | J47: =IFERROR(INDEX(BDH($G$47,$H$47,'01_Parametros'!$B$3,'01_Parametros'!$B$3,"Days=A","Fill=B","Dir=H"),1,2),BDH($G$47,$H$47,'01_Parametros'!$B$3,'01_Parametros'!$B$3,"Days=A","Fill=B")) | K47: =IFERROR(INDEX(BDH($G$47,$H$47,'01_Parametros'!$B$5,'01_Parametros'!$B$5,"Days=A","Fill=B","Dir=H"),1,2),BDH($G$47,$H$47,'01_Parametros'!$B$5,'01_Parametros'!$B$5,"Days=A","Fill=B")) | L47: =IFERROR(INDEX(BDH($G$47,$H$47,'01_Parametros'!$B$6,'01_Parametros'!$B$6,"Days=A","Fill=B","Dir=H"),1,2),BDH($G$47,$H$47,'01_Parametros'!$B$6,'01_Parametros'!$B$6,"Days=A","Fill=B")) | M47: =IFERROR(INDEX(BDH($G$47,$H$47,'01_Parametros'!$B$7,'01_Parametros'!$B$7,"Days=A","Fill=B","Dir=H"),1,2),BDH($G$47,$H$47,'01_Parametros'!$B$7,'01_Parametros'!$B$7,"Days=A","Fill=B")) | N47: Japan JGB 10Y
A48: 47 | B48: yield_curve | C48: BR | D48: BR_GOV | E48: 10Y | F48: 10 | G48: GEBR10Y Index | H48: PX_LAST | I48: percent | J48: =IFERROR(INDEX(BDH($G$48,$H$48,'01_Parametros'!$B$3,'01_Parametros'!$B$3,"Days=A","Fill=B","Dir=H"),1,2),BDH($G$48,$H$48,'01_Parametros'!$B$3,'01_Parametros'!$B$3,"Days=A","Fill=B")) | K48: =IFERROR(INDEX(BDH($G$48,$H$48,'01_Parametros'!$B$5,'01_Parametros'!$B$5,"Days=A","Fill=B","Dir=H"),1,2),BDH($G$48,$H$48,'01_Parametros'!$B$5,'01_Parametros'!$B$5,"Days=A","Fill=B")) | L48: =IFERROR(INDEX(BDH($G$48,$H$48,'01_Parametros'!$B$6,'01_Parametros'!$B$6,"Days=A","Fill=B","Dir=H"),1,2),BDH($G$48,$H$48,'01_Parametros'!$B$6,'01_Parametros'!$B$6,"Days=A","Fill=B")) | M48: =IFERROR(INDEX(BDH($G$48,$H$48,'01_Parametros'!$B$7,'01_Parametros'!$B$7,"Days=A","Fill=B","Dir=H"),1,2),BDH($G$48,$H$48,'01_Parametros'!$B$7,'01_Parametros'!$B$7,"Days=A","Fill=B")) | N48: Brazil 10Y — confirmar
A49: 48 | B49: yield_curve | C49: MX | D49: MX_MBONO | E49: 10Y | F49: 10 | G49: GMXN10YR Index | H49: PX_LAST | I49: percent | J49: =IFERROR(INDEX(BDH($G$49,$H$49,'01_Parametros'!$B$3,'01_Parametros'!$B$3,"Days=A","Fill=B","Dir=H"),1,2),BDH($G$49,$H$49,'01_Parametros'!$B$3,'01_Parametros'!$B$3,"Days=A","Fill=B")) | K49: =IFERROR(INDEX(BDH($G$49,$H$49,'01_Parametros'!$B$5,'01_Parametros'!$B$5,"Days=A","Fill=B","Dir=H"),1,2),BDH($G$49,$H$49,'01_Parametros'!$B$5,'01_Parametros'!$B$5,"Days=A","Fill=B")) | L49: =IFERROR(INDEX(BDH($G$49,$H$49,'01_Parametros'!$B$6,'01_Parametros'!$B$6,"Days=A","Fill=B","Dir=H"),1,2),BDH($G$49,$H$49,'01_Parametros'!$B$6,'01_Parametros'!$B$6,"Days=A","Fill=B")) | M49: =IFERROR(INDEX(BDH($G$49,$H$49,'01_Parametros'!$B$7,'01_Parametros'!$B$7,"Days=A","Fill=B","Dir=H"),1,2),BDH($G$49,$H$49,'01_Parametros'!$B$7,'01_Parametros'!$B$7,"Days=A","Fill=B")) | N49: Mexico MBONO 10Y — confirmar
A50: 49 | B50: yield_curve | C50: CO | D50: CO_TES | E50: 10Y | F50: 10 | G50: COGR10Y Index | H50: PX_LAST | I50: percent | J50: =IFERROR(INDEX(BDH($G$50,$H$50,'01_Parametros'!$B$3,'01_Parametros'!$B$3,"Days=A","Fill=B","Dir=H"),1,2),BDH($G$50,$H$50,'01_Parametros'!$B$3,'01_Parametros'!$B$3,"Days=A","Fill=B")) | K50: =IFERROR(INDEX(BDH($G$50,$H$50,'01_Parametros'!$B$5,'01_Parametros'!$B$5,"Days=A","Fill=B","Dir=H"),1,2),BDH($G$50,$H$50,'01_Parametros'!$B$5,'01_Parametros'!$B$5,"Days=A","Fill=B")) | L50: =IFERROR(INDEX(BDH($G$50,$H$50,'01_Parametros'!$B$6,'01_Parametros'!$B$6,"Days=A","Fill=B","Dir=H"),1,2),BDH($G$50,$H$50,'01_Parametros'!$B$6,'01_Parametros'!$B$6,"Days=A","Fill=B")) | M50: =IFERROR(INDEX(BDH($G$50,$H$50,'01_Parametros'!$B$7,'01_Parametros'!$B$7,"Days=A","Fill=B","Dir=H"),1,2),BDH($G$50,$H$50,'01_Parametros'!$B$7,'01_Parametros'!$B$7,"Days=A","Fill=B")) | N50: Colombia TES 10Y — confirmar
A51: 50 | B51: fx | C51: — | D51: EURUSD | E51: SPOT | F51: 0 | G51: EURUSD Curncy | H51: PX_LAST | I51: rate | J51: =IFERROR(INDEX(BDH($G$51,$H$51,'01_Parametros'!$B$3,'01_Parametros'!$B$3,"Days=A","Fill=B","Dir=H"),1,2),BDH($G$51,$H$51,'01_Parametros'!$B$3,'01_Parametros'!$B$3,"Days=A","Fill=B")) | K51: =IFERROR(INDEX(BDH($G$51,$H$51,'01_Parametros'!$B$5,'01_Parametros'!$B$5,"Days=A","Fill=B","Dir=H"),1,2),BDH($G$51,$H$51,'01_Parametros'!$B$5,'01_Parametros'!$B$5,"Days=A","Fill=B")) | L51: =IFERROR(INDEX(BDH($G$51,$H$51,'01_Parametros'!$B$6,'01_Parametros'!$B$6,"Days=A","Fill=B","Dir=H"),1,2),BDH($G$51,$H$51,'01_Parametros'!$B$6,'01_Parametros'!$B$6,"Days=A","Fill=B")) | M51: =IFERROR(INDEX(BDH($G$51,$H$51,'01_Parametros'!$B$7,'01_Parametros'!$B$7,"Days=A","Fill=B","Dir=H"),1,2),BDH($G$51,$H$51,'01_Parametros'!$B$7,'01_Parametros'!$B$7,"Days=A","Fill=B")) | N51: EUR/USD spot
A52: 51 | B52: fx | C52: — | D52: GBPUSD | E52: SPOT | F52: 0 | G52: GBPUSD Curncy | H52: PX_LAST | I52: rate | J52: =IFERROR(INDEX(BDH($G$52,$H$52,'01_Parametros'!$B$3,'01_Parametros'!$B$3,"Days=A","Fill=B","Dir=H"),1,2),BDH($G$52,$H$52,'01_Parametros'!$B$3,'01_Parametros'!$B$3,"Days=A","Fill=B")) | K52: =IFERROR(INDEX(BDH($G$52,$H$52,'01_Parametros'!$B$5,'01_Parametros'!$B$5,"Days=A","Fill=B","Dir=H"),1,2),BDH($G$52,$H$52,'01_Parametros'!$B$5,'01_Parametros'!$B$5,"Days=A","Fill=B")) | L52: =IFERROR(INDEX(BDH($G$52,$H$52,'01_Parametros'!$B$6,'01_Parametros'!$B$6,"Days=A","Fill=B","Dir=H"),1,2),BDH($G$52,$H$52,'01_Parametros'!$B$6,'01_Parametros'!$B$6,"Days=A","Fill=B")) | M52: =IFERROR(INDEX(BDH($G$52,$H$52,'01_Parametros'!$B$7,'01_Parametros'!$B$7,"Days=A","Fill=B","Dir=H"),1,2),BDH($G$52,$H$52,'01_Parametros'!$B$7,'01_Parametros'!$B$7,"Days=A","Fill=B")) | N52: GBP/USD spot
A53: 52 | B53: fx | C53: — | D53: USDJPY | E53: SPOT | F53: 0 | G53: USDJPY Curncy | H53: PX_LAST | I53: rate | J53: =IFERROR(INDEX(BDH($G$53,$H$53,'01_Parametros'!$B$3,'01_Parametros'!$B$3,"Days=A","Fill=B","Dir=H"),1,2),BDH($G$53,$H$53,'01_Parametros'!$B$3,'01_Parametros'!$B$3,"Days=A","Fill=B")) | K53: =IFERROR(INDEX(BDH($G$53,$H$53,'01_Parametros'!$B$5,'01_Parametros'!$B$5,"Days=A","Fill=B","Dir=H"),1,2),BDH($G$53,$H$53,'01_Parametros'!$B$5,'01_Parametros'!$B$5,"Days=A","Fill=B")) | L53: =IFERROR(INDEX(BDH($G$53,$H$53,'01_Parametros'!$B$6,'01_Parametros'!$B$6,"Days=A","Fill=B","Dir=H"),1,2),BDH($G$53,$H$53,'01_Parametros'!$B$6,'01_Parametros'!$B$6,"Days=A","Fill=B")) | M53: =IFERROR(INDEX(BDH($G$53,$H$53,'01_Parametros'!$B$7,'01_Parametros'!$B$7,"Days=A","Fill=B","Dir=H"),1,2),BDH($G$53,$H$53,'01_Parametros'!$B$7,'01_Parametros'!$B$7,"Days=A","Fill=B")) | N53: USD/JPY spot
A54: 53 | B54: fx | C54: — | D54: USDCNY | E54: SPOT | F54: 0 | G54: USDCNY Curncy | H54: PX_LAST | I54: rate | J54: =IFERROR(INDEX(BDH($G$54,$H$54,'01_Parametros'!$B$3,'01_Parametros'!$B$3,"Days=A","Fill=B","Dir=H"),1,2),BDH($G$54,$H$54,'01_Parametros'!$B$3,'01_Parametros'!$B$3,"Days=A","Fill=B")) | K54: =IFERROR(INDEX(BDH($G$54,$H$54,'01_Parametros'!$B$5,'01_Parametros'!$B$5,"Days=A","Fill=B","Dir=H"),1,2),BDH($G$54,$H$54,'01_Parametros'!$B$5,'01_Parametros'!$B$5,"Days=A","Fill=B")) | L54: =IFERROR(INDEX(BDH($G$54,$H$54,'01_Parametros'!$B$6,'01_Parametros'!$B$6,"Days=A","Fill=B","Dir=H"),1,2),BDH($G$54,$H$54,'01_Parametros'!$B$6,'01_Parametros'!$B$6,"Days=A","Fill=B")) | M54: =IFERROR(INDEX(BDH($G$54,$H$54,'01_Parametros'!$B$7,'01_Parametros'!$B$7,"Days=A","Fill=B","Dir=H"),1,2),BDH($G$54,$H$54,'01_Parametros'!$B$7,'01_Parametros'!$B$7,"Days=A","Fill=B")) | N54: USD/CNY spot
A55: 54 | B55: fx | C55: — | D55: USDBRL | E55: SPOT | F55: 0 | G55: USDBRL Curncy | H55: PX_LAST | I55: rate | J55: =IFERROR(INDEX(BDH($G$55,$H$55,'01_Parametros'!$B$3,'01_Parametros'!$B$3,"Days=A","Fill=B","Dir=H"),1,2),BDH($G$55,$H$55,'01_Parametros'!$B$3,'01_Parametros'!$B$3,"Days=A","Fill=B")) | K55: =IFERROR(INDEX(BDH($G$55,$H$55,'01_Parametros'!$B$5,'01_Parametros'!$B$5,"Days=A","Fill=B","Dir=H"),1,2),BDH($G$55,$H$55,'01_Parametros'!$B$5,'01_Parametros'!$B$5,"Days=A","Fill=B")) | L55: =IFERROR(INDEX(BDH($G$55,$H$55,'01_Parametros'!$B$6,'01_Parametros'!$B$6,"Days=A","Fill=B","Dir=H"),1,2),BDH($G$55,$H$55,'01_Parametros'!$B$6,'01_Parametros'!$B$6,"Days=A","Fill=B")) | M55: =IFERROR(INDEX(BDH($G$55,$H$55,'01_Parametros'!$B$7,'01_Parametros'!$B$7,"Days=A","Fill=B","Dir=H"),1,2),BDH($G$55,$H$55,'01_Parametros'!$B$7,'01_Parametros'!$B$7,"Days=A","Fill=B")) | N55: USD/BRL spot
A56: 55 | B56: fx | C56: — | D56: USDMXN | E56: SPOT | F56: 0 | G56: USDMXN Curncy | H56: PX_LAST | I56: rate | J56: =IFERROR(INDEX(BDH($G$56,$H$56,'01_Parametros'!$B$3,'01_Parametros'!$B$3,"Days=A","Fill=B","Dir=H"),1,2),BDH($G$56,$H$56,'01_Parametros'!$B$3,'01_Parametros'!$B$3,"Days=A","Fill=B")) | K56: =IFERROR(INDEX(BDH($G$56,$H$56,'01_Parametros'!$B$5,'01_Parametros'!$B$5,"Days=A","Fill=B","Dir=H"),1,2),BDH($G$56,$H$56,'01_Parametros'!$B$5,'01_Parametros'!$B$5,"Days=A","Fill=B")) | L56: =IFERROR(INDEX(BDH($G$56,$H$56,'01_Parametros'!$B$6,'01_Parametros'!$B$6,"Days=A","Fill=B","Dir=H"),1,2),BDH($G$56,$H$56,'01_Parametros'!$B$6,'01_Parametros'!$B$6,"Days=A","Fill=B")) | M56: =IFERROR(INDEX(BDH($G$56,$H$56,'01_Parametros'!$B$7,'01_Parametros'!$B$7,"Days=A","Fill=B","Dir=H"),1,2),BDH($G$56,$H$56,'01_Parametros'!$B$7,'01_Parametros'!$B$7,"Days=A","Fill=B")) | N56: USD/MXN spot
A57: 56 | B57: fx | C57: — | D57: USDCOP | E57: SPOT | F57: 0 | G57: USDCOP Curncy | H57: PX_LAST | I57: rate | J57: =IFERROR(INDEX(BDH($G$57,$H$57,'01_Parametros'!$B$3,'01_Parametros'!$B$3,"Days=A","Fill=B","Dir=H"),1,2),BDH($G$57,$H$57,'01_Parametros'!$B$3,'01_Parametros'!$B$3,"Days=A","Fill=B")) | K57: =IFERROR(INDEX(BDH($G$57,$H$57,'01_Parametros'!$B$5,'01_Parametros'!$B$5,"Days=A","Fill=B","Dir=H"),1,2),BDH($G$57,$H$57,'01_Parametros'!$B$5,'01_Parametros'!$B$5,"Days=A","Fill=B")) | L57: =IFERROR(INDEX(BDH($G$57,$H$57,'01_Parametros'!$B$6,'01_Parametros'!$B$6,"Days=A","Fill=B","Dir=H"),1,2),BDH($G$57,$H$57,'01_Parametros'!$B$6,'01_Parametros'!$B$6,"Days=A","Fill=B")) | M57: =IFERROR(INDEX(BDH($G$57,$H$57,'01_Parametros'!$B$7,'01_Parametros'!$B$7,"Days=A","Fill=B","Dir=H"),1,2),BDH($G$57,$H$57,'01_Parametros'!$B$7,'01_Parametros'!$B$7,"Days=A","Fill=B")) | N57: USD/COP spot
A58: 57 | B58: fx | C58: — | D58: USDCLP | E58: SPOT | F58: 0 | G58: USDCLP Curncy | H58: PX_LAST | I58: rate | J58: =IFERROR(INDEX(BDH($G$58,$H$58,'01_Parametros'!$B$3,'01_Parametros'!$B$3,"Days=A","Fill=B","Dir=H"),1,2),BDH($G$58,$H$58,'01_Parametros'!$B$3,'01_Parametros'!$B$3,"Days=A","Fill=B")) | K58: =IFERROR(INDEX(BDH($G$58,$H$58,'01_Parametros'!$B$5,'01_Parametros'!$B$5,"Days=A","Fill=B","Dir=H"),1,2),BDH($G$58,$H$58,'01_Parametros'!$B$5,'01_Parametros'!$B$5,"Days=A","Fill=B")) | L58: =IFERROR(INDEX(BDH($G$58,$H$58,'01_Parametros'!$B$6,'01_Parametros'!$B$6,"Days=A","Fill=B","Dir=H"),1,2),BDH($G$58,$H$58,'01_Parametros'!$B$6,'01_Parametros'!$B$6,"Days=A","Fill=B")) | M58: =IFERROR(INDEX(BDH($G$58,$H$58,'01_Parametros'!$B$7,'01_Parametros'!$B$7,"Days=A","Fill=B","Dir=H"),1,2),BDH($G$58,$H$58,'01_Parametros'!$B$7,'01_Parametros'!$B$7,"Days=A","Fill=B")) | N58: USD/CLP spot
A59: 58 | B59: fx | C59: — | D59: DXY | E59: SPOT | F59: 0 | G59: DXY Curncy | H59: PX_LAST | I59: index | J59: =IFERROR(INDEX(BDH($G$59,$H$59,'01_Parametros'!$B$3,'01_Parametros'!$B$3,"Days=A","Fill=B","Dir=H"),1,2),BDH($G$59,$H$59,'01_Parametros'!$B$3,'01_Parametros'!$B$3,"Days=A","Fill=B")) | K59: =IFERROR(INDEX(BDH($G$59,$H$59,'01_Parametros'!$B$5,'01_Parametros'!$B$5,"Days=A","Fill=B","Dir=H"),1,2),BDH($G$59,$H$59,'01_Parametros'!$B$5,'01_Parametros'!$B$5,"Days=A","Fill=B")) | L59: =IFERROR(INDEX(BDH($G$59,$H$59,'01_Parametros'!$B$6,'01_Parametros'!$B$6,"Days=A","Fill=B","Dir=H"),1,2),BDH($G$59,$H$59,'01_Parametros'!$B$6,'01_Parametros'!$B$6,"Days=A","Fill=B")) | M59: =IFERROR(INDEX(BDH($G$59,$H$59,'01_Parametros'!$B$7,'01_Parametros'!$B$7,"Days=A","Fill=B","Dir=H"),1,2),BDH($G$59,$H$59,'01_Parametros'!$B$7,'01_Parametros'!$B$7,"Days=A","Fill=B")) | N59: Dollar Index
A60: 59 | B60: credit_index | C60: EM | D60: EMBI_GLOBAL_SPRD | E60: ALL | F60: 0 | G60: JPEIDIVR Index | H60: PX_LAST | I60: bps | J60: =IFERROR(INDEX(BDH($G$60,$H$60,'01_Parametros'!$B$3,'01_Parametros'!$B$3,"Days=A","Fill=B","Dir=H"),1,2),BDH($G$60,$H$60,'01_Parametros'!$B$3,'01_Parametros'!$B$3,"Days=A","Fill=B")) | K60: =IFERROR(INDEX(BDH($G$60,$H$60,'01_Parametros'!$B$5,'01_Parametros'!$B$5,"Days=A","Fill=B","Dir=H"),1,2),BDH($G$60,$H$60,'01_Parametros'!$B$5,'01_Parametros'!$B$5,"Days=A","Fill=B")) | L60: =IFERROR(INDEX(BDH($G$60,$H$60,'01_Parametros'!$B$6,'01_Parametros'!$B$6,"Days=A","Fill=B","Dir=H"),1,2),BDH($G$60,$H$60,'01_Parametros'!$B$6,'01_Parametros'!$B$6,"Days=A","Fill=B")) | M60: =IFERROR(INDEX(BDH($G$60,$H$60,'01_Parametros'!$B$7,'01_Parametros'!$B$7,"Days=A","Fill=B","Dir=H"),1,2),BDH($G$60,$H$60,'01_Parametros'!$B$7,'01_Parametros'!$B$7,"Days=A","Fill=B")) | N60: EMBI Global Diversified — confirmar
A61: 60 | B61: credit_index | C61: LATAM | D61: EMBI_LATAM_SPRD | E61: ALL | F61: 0 | G61: JPEMLAT Index | H61: PX_LAST | I61: bps | J61: =IFERROR(INDEX(BDH($G$61,$H$61,'01_Parametros'!$B$3,'01_Parametros'!$B$3,"Days=A","Fill=B","Dir=H"),1,2),BDH($G$61,$H$61,'01_Parametros'!$B$3,'01_Parametros'!$B$3,"Days=A","Fill=B")) | K61: =IFERROR(INDEX(BDH($G$61,$H$61,'01_Parametros'!$B$5,'01_Parametros'!$B$5,"Days=A","Fill=B","Dir=H"),1,2),BDH($G$61,$H$61,'01_Parametros'!$B$5,'01_Parametros'!$B$5,"Days=A","Fill=B")) | L61: =IFERROR(INDEX(BDH($G$61,$H$61,'01_Parametros'!$B$6,'01_Parametros'!$B$6,"Days=A","Fill=B","Dir=H"),1,2),BDH($G$61,$H$61,'01_Parametros'!$B$6,'01_Parametros'!$B$6,"Days=A","Fill=B")) | M61: =IFERROR(INDEX(BDH($G$61,$H$61,'01_Parametros'!$B$7,'01_Parametros'!$B$7,"Days=A","Fill=B","Dir=H"),1,2),BDH($G$61,$H$61,'01_Parametros'!$B$7,'01_Parametros'!$B$7,"Days=A","Fill=B")) | N61: EMBI Latam — confirmar
A62: 61 | B62: credit_index | C62: PA | D62: EMBI_PANAMA_SPRD | E62: ALL | F62: 0 | G62: JPGCPANS Index | H62: PX_LAST | I62: bps | J62: =IFERROR(INDEX(BDH($G$62,$H$62,'01_Parametros'!$B$3,'01_Parametros'!$B$3,"Days=A","Fill=B","Dir=H"),1,2),BDH($G$62,$H$62,'01_Parametros'!$B$3,'01_Parametros'!$B$3,"Days=A","Fill=B")) | K62: =IFERROR(INDEX(BDH($G$62,$H$62,'01_Parametros'!$B$5,'01_Parametros'!$B$5,"Days=A","Fill=B","Dir=H"),1,2),BDH($G$62,$H$62,'01_Parametros'!$B$5,'01_Parametros'!$B$5,"Days=A","Fill=B")) | L62: =IFERROR(INDEX(BDH($G$62,$H$62,'01_Parametros'!$B$6,'01_Parametros'!$B$6,"Days=A","Fill=B","Dir=H"),1,2),BDH($G$62,$H$62,'01_Parametros'!$B$6,'01_Parametros'!$B$6,"Days=A","Fill=B")) | M62: =IFERROR(INDEX(BDH($G$62,$H$62,'01_Parametros'!$B$7,'01_Parametros'!$B$7,"Days=A","Fill=B","Dir=H"),1,2),BDH($G$62,$H$62,'01_Parametros'!$B$7,'01_Parametros'!$B$7,"Days=A","Fill=B")) | N62: EMBI Panama spread — confirmar
A63: 62 | B63: credit_index | C63: VE | D63: EMBI_VEN_SPRD | E63: ALL | F63: 0 | G63: JPGCVENS Index | H63: PX_LAST | I63: bps | J63: =IFERROR(INDEX(BDH($G$63,$H$63,'01_Parametros'!$B$3,'01_Parametros'!$B$3,"Days=A","Fill=B","Dir=H"),1,2),BDH($G$63,$H$63,'01_Parametros'!$B$3,'01_Parametros'!$B$3,"Days=A","Fill=B")) | K63: =IFERROR(INDEX(BDH($G$63,$H$63,'01_Parametros'!$B$5,'01_Parametros'!$B$5,"Days=A","Fill=B","Dir=H"),1,2),BDH($G$63,$H$63,'01_Parametros'!$B$5,'01_Parametros'!$B$5,"Days=A","Fill=B")) | L63: =IFERROR(INDEX(BDH($G$63,$H$63,'01_Parametros'!$B$6,'01_Parametros'!$B$6,"Days=A","Fill=B","Dir=H"),1,2),BDH($G$63,$H$63,'01_Parametros'!$B$6,'01_Parametros'!$B$6,"Days=A","Fill=B")) | M63: =IFERROR(INDEX(BDH($G$63,$H$63,'01_Parametros'!$B$7,'01_Parametros'!$B$7,"Days=A","Fill=B","Dir=H"),1,2),BDH($G$63,$H$63,'01_Parametros'!$B$7,'01_Parametros'!$B$7,"Days=A","Fill=B")) | N63: EMBI Venezuela spread — confirmar
A64: 63 | B64: credit_index | C64: US | D64: ICE_C0A0_YIELD | E64: ALL | F64: 0 | G64: C0A0 Index | H64: INDEX_YIELD_TO_WORST | I64: percent | J64: =IFERROR(INDEX(BDH($G$64,$H$64,'01_Parametros'!$B$3,'01_Parametros'!$B$3,"Days=A","Fill=B","Dir=H"),1,2),BDH($G$64,$H$64,'01_Parametros'!$B$3,'01_Parametros'!$B$3,"Days=A","Fill=B")) | K64: =IFERROR(INDEX(BDH($G$64,$H$64,'01_Parametros'!$B$5,'01_Parametros'!$B$5,"Days=A","Fill=B","Dir=H"),1,2),BDH($G$64,$H$64,'01_Parametros'!$B$5,'01_Parametros'!$B$5,"Days=A","Fill=B")) | L64: =IFERROR(INDEX(BDH($G$64,$H$64,'01_Parametros'!$B$6,'01_Parametros'!$B$6,"Days=A","Fill=B","Dir=H"),1,2),BDH($G$64,$H$64,'01_Parametros'!$B$6,'01_Parametros'!$B$6,"Days=A","Fill=B")) | M64: =IFERROR(INDEX(BDH($G$64,$H$64,'01_Parametros'!$B$7,'01_Parametros'!$B$7,"Days=A","Fill=B","Dir=H"),1,2),BDH($G$64,$H$64,'01_Parametros'!$B$7,'01_Parametros'!$B$7,"Days=A","Fill=B")) | N64: ICE BofA US Corporate Master YTW
A65: 64 | B65: credit_index | C65: US | D65: ICE_C0A0_OAS | E65: ALL | F65: 0 | G65: C0A0 Index | H65: OAS_SPREAD_BID | I65: bps | J65: =IFERROR(INDEX(BDH($G$65,$H$65,'01_Parametros'!$B$3,'01_Parametros'!$B$3,"Days=A","Fill=B","Dir=H"),1,2),BDH($G$65,$H$65,'01_Parametros'!$B$3,'01_Parametros'!$B$3,"Days=A","Fill=B")) | K65: =IFERROR(INDEX(BDH($G$65,$H$65,'01_Parametros'!$B$5,'01_Parametros'!$B$5,"Days=A","Fill=B","Dir=H"),1,2),BDH($G$65,$H$65,'01_Parametros'!$B$5,'01_Parametros'!$B$5,"Days=A","Fill=B")) | L65: =IFERROR(INDEX(BDH($G$65,$H$65,'01_Parametros'!$B$6,'01_Parametros'!$B$6,"Days=A","Fill=B","Dir=H"),1,2),BDH($G$65,$H$65,'01_Parametros'!$B$6,'01_Parametros'!$B$6,"Days=A","Fill=B")) | M65: =IFERROR(INDEX(BDH($G$65,$H$65,'01_Parametros'!$B$7,'01_Parametros'!$B$7,"Days=A","Fill=B","Dir=H"),1,2),BDH($G$65,$H$65,'01_Parametros'!$B$7,'01_Parametros'!$B$7,"Days=A","Fill=B")) | N65: ICE BofA US Corp Master OAS
A66: 65 | B66: credit_index | C66: US | D66: ICE_C0A1_AAA_OAS | E66: ALL | F66: 0 | G66: C0A1 Index | H66: OAS_SPREAD_BID | I66: bps | J66: =IFERROR(INDEX(BDH($G$66,$H$66,'01_Parametros'!$B$3,'01_Parametros'!$B$3,"Days=A","Fill=B","Dir=H"),1,2),BDH($G$66,$H$66,'01_Parametros'!$B$3,'01_Parametros'!$B$3,"Days=A","Fill=B")) | K66: =IFERROR(INDEX(BDH($G$66,$H$66,'01_Parametros'!$B$5,'01_Parametros'!$B$5,"Days=A","Fill=B","Dir=H"),1,2),BDH($G$66,$H$66,'01_Parametros'!$B$5,'01_Parametros'!$B$5,"Days=A","Fill=B")) | L66: =IFERROR(INDEX(BDH($G$66,$H$66,'01_Parametros'!$B$6,'01_Parametros'!$B$6,"Days=A","Fill=B","Dir=H"),1,2),BDH($G$66,$H$66,'01_Parametros'!$B$6,'01_Parametros'!$B$6,"Days=A","Fill=B")) | M66: =IFERROR(INDEX(BDH($G$66,$H$66,'01_Parametros'!$B$7,'01_Parametros'!$B$7,"Days=A","Fill=B","Dir=H"),1,2),BDH($G$66,$H$66,'01_Parametros'!$B$7,'01_Parametros'!$B$7,"Days=A","Fill=B")) | N66: ICE BofA US Corp AAA OAS
A67: 66 | B67: credit_index | C67: US | D67: ICE_C0A2_AA_OAS | E67: ALL | F67: 0 | G67: C0A2 Index | H67: OAS_SPREAD_BID | I67: bps | J67: =IFERROR(INDEX(BDH($G$67,$H$67,'01_Parametros'!$B$3,'01_Parametros'!$B$3,"Days=A","Fill=B","Dir=H"),1,2),BDH($G$67,$H$67,'01_Parametros'!$B$3,'01_Parametros'!$B$3,"Days=A","Fill=B")) | K67: =IFERROR(INDEX(BDH($G$67,$H$67,'01_Parametros'!$B$5,'01_Parametros'!$B$5,"Days=A","Fill=B","Dir=H"),1,2),BDH($G$67,$H$67,'01_Parametros'!$B$5,'01_Parametros'!$B$5,"Days=A","Fill=B")) | L67: =IFERROR(INDEX(BDH($G$67,$H$67,'01_Parametros'!$B$6,'01_Parametros'!$B$6,"Days=A","Fill=B","Dir=H"),1,2),BDH($G$67,$H$67,'01_Parametros'!$B$6,'01_Parametros'!$B$6,"Days=A","Fill=B")) | M67: =IFERROR(INDEX(BDH($G$67,$H$67,'01_Parametros'!$B$7,'01_Parametros'!$B$7,"Days=A","Fill=B","Dir=H"),1,2),BDH($G$67,$H$67,'01_Parametros'!$B$7,'01_Parametros'!$B$7,"Days=A","Fill=B")) | N67: ICE BofA US Corp AA OAS
A68: 67 | B68: credit_index | C68: US | D68: ICE_C0A3_A_OAS | E68: ALL | F68: 0 | G68: C0A3 Index | H68: OAS_SPREAD_BID | I68: bps | J68: =IFERROR(INDEX(BDH($G$68,$H$68,'01_Parametros'!$B$3,'01_Parametros'!$B$3,"Days=A","Fill=B","Dir=H"),1,2),BDH($G$68,$H$68,'01_Parametros'!$B$3,'01_Parametros'!$B$3,"Days=A","Fill=B")) | K68: =IFERROR(INDEX(BDH($G$68,$H$68,'01_Parametros'!$B$5,'01_Parametros'!$B$5,"Days=A","Fill=B","Dir=H"),1,2),BDH($G$68,$H$68,'01_Parametros'!$B$5,'01_Parametros'!$B$5,"Days=A","Fill=B")) | L68: =IFERROR(INDEX(BDH($G$68,$H$68,'01_Parametros'!$B$6,'01_Parametros'!$B$6,"Days=A","Fill=B","Dir=H"),1,2),BDH($G$68,$H$68,'01_Parametros'!$B$6,'01_Parametros'!$B$6,"Days=A","Fill=B")) | M68: =IFERROR(INDEX(BDH($G$68,$H$68,'01_Parametros'!$B$7,'01_Parametros'!$B$7,"Days=A","Fill=B","Dir=H"),1,2),BDH($G$68,$H$68,'01_Parametros'!$B$7,'01_Parametros'!$B$7,"Days=A","Fill=B")) | N68: ICE BofA US Corp A OAS
A69: 68 | B69: credit_index | C69: US | D69: ICE_C0A4_BBB_OAS | E69: ALL | F69: 0 | G69: C0A4 Index | H69: OAS_SPREAD_BID | I69: bps | J69: =IFERROR(INDEX(BDH($G$69,$H$69,'01_Parametros'!$B$3,'01_Parametros'!$B$3,"Days=A","Fill=B","Dir=H"),1,2),BDH($G$69,$H$69,'01_Parametros'!$B$3,'01_Parametros'!$B$3,"Days=A","Fill=B")) | K69: =IFERROR(INDEX(BDH($G$69,$H$69,'01_Parametros'!$B$5,'01_Parametros'!$B$5,"Days=A","Fill=B","Dir=H"),1,2),BDH($G$69,$H$69,'01_Parametros'!$B$5,'01_Parametros'!$B$5,"Days=A","Fill=B")) | L69: =IFERROR(INDEX(BDH($G$69,$H$69,'01_Parametros'!$B$6,'01_Parametros'!$B$6,"Days=A","Fill=B","Dir=H"),1,2),BDH($G$69,$H$69,'01_Parametros'!$B$6,'01_Parametros'!$B$6,"Days=A","Fill=B")) | M69: =IFERROR(INDEX(BDH($G$69,$H$69,'01_Parametros'!$B$7,'01_Parametros'!$B$7,"Days=A","Fill=B","Dir=H"),1,2),BDH($G$69,$H$69,'01_Parametros'!$B$7,'01_Parametros'!$B$7,"Days=A","Fill=B")) | N69: ICE BofA US Corp BBB OAS
A70: 69 | B70: credit_index | C70: US | D70: ICE_H0A0_HY_YIELD | E70: ALL | F70: 0 | G70: H0A0 Index | H70: INDEX_YIELD_TO_WORST | I70: percent | J70: =IFERROR(INDEX(BDH($G$70,$H$70,'01_Parametros'!$B$3,'01_Parametros'!$B$3,"Days=A","Fill=B","Dir=H"),1,2),BDH($G$70,$H$70,'01_Parametros'!$B$3,'01_Parametros'!$B$3,"Days=A","Fill=B")) | K70: =IFERROR(INDEX(BDH($G$70,$H$70,'01_Parametros'!$B$5,'01_Parametros'!$B$5,"Days=A","Fill=B","Dir=H"),1,2),BDH($G$70,$H$70,'01_Parametros'!$B$5,'01_Parametros'!$B$5,"Days=A","Fill=B")) | L70: =IFERROR(INDEX(BDH($G$70,$H$70,'01_Parametros'!$B$6,'01_Parametros'!$B$6,"Days=A","Fill=B","Dir=H"),1,2),BDH($G$70,$H$70,'01_Parametros'!$B$6,'01_Parametros'!$B$6,"Days=A","Fill=B")) | M70: =IFERROR(INDEX(BDH($G$70,$H$70,'01_Parametros'!$B$7,'01_Parametros'!$B$7,"Days=A","Fill=B","Dir=H"),1,2),BDH($G$70,$H$70,'01_Parametros'!$B$7,'01_Parametros'!$B$7,"Days=A","Fill=B")) | N70: ICE BofA US HY Master YTW
A71: 70 | B71: credit_index | C71: US | D71: ICE_H0A0_HY_OAS | E71: ALL | F71: 0 | G71: H0A0 Index | H71: OAS_SPREAD_BID | I71: bps | J71: =IFERROR(INDEX(BDH($G$71,$H$71,'01_Parametros'!$B$3,'01_Parametros'!$B$3,"Days=A","Fill=B","Dir=H"),1,2),BDH($G$71,$H$71,'01_Parametros'!$B$3,'01_Parametros'!$B$3,"Days=A","Fill=B")) | K71: =IFERROR(INDEX(BDH($G$71,$H$71,'01_Parametros'!$B$5,'01_Parametros'!$B$5,"Days=A","Fill=B","Dir=H"),1,2),BDH($G$71,$H$71,'01_Parametros'!$B$5,'01_Parametros'!$B$5,"Days=A","Fill=B")) | L71: =IFERROR(INDEX(BDH($G$71,$H$71,'01_Parametros'!$B$6,'01_Parametros'!$B$6,"Days=A","Fill=B","Dir=H"),1,2),BDH($G$71,$H$71,'01_Parametros'!$B$6,'01_Parametros'!$B$6,"Days=A","Fill=B")) | M71: =IFERROR(INDEX(BDH($G$71,$H$71,'01_Parametros'!$B$7,'01_Parametros'!$B$7,"Days=A","Fill=B","Dir=H"),1,2),BDH($G$71,$H$71,'01_Parametros'!$B$7,'01_Parametros'!$B$7,"Days=A","Fill=B")) | N71: ICE BofA US HY Master OAS
A72: 71 | B72: credit_index | C72: US | D72: ICE_H0A1_BB_OAS | E72: ALL | F72: 0 | G72: H0A1 Index | H72: OAS_SPREAD_BID | I72: bps | J72: =IFERROR(INDEX(BDH($G$72,$H$72,'01_Parametros'!$B$3,'01_Parametros'!$B$3,"Days=A","Fill=B","Dir=H"),1,2),BDH($G$72,$H$72,'01_Parametros'!$B$3,'01_Parametros'!$B$3,"Days=A","Fill=B")) | K72: =IFERROR(INDEX(BDH($G$72,$H$72,'01_Parametros'!$B$5,'01_Parametros'!$B$5,"Days=A","Fill=B","Dir=H"),1,2),BDH($G$72,$H$72,'01_Parametros'!$B$5,'01_Parametros'!$B$5,"Days=A","Fill=B")) | L72: =IFERROR(INDEX(BDH($G$72,$H$72,'01_Parametros'!$B$6,'01_Parametros'!$B$6,"Days=A","Fill=B","Dir=H"),1,2),BDH($G$72,$H$72,'01_Parametros'!$B$6,'01_Parametros'!$B$6,"Days=A","Fill=B")) | M72: =IFERROR(INDEX(BDH($G$72,$H$72,'01_Parametros'!$B$7,'01_Parametros'!$B$7,"Days=A","Fill=B","Dir=H"),1,2),BDH($G$72,$H$72,'01_Parametros'!$B$7,'01_Parametros'!$B$7,"Days=A","Fill=B")) | N72: ICE BofA US HY BB OAS
A73: 72 | B73: credit_index | C73: US | D73: ICE_H0A2_B_OAS | E73: ALL | F73: 0 | G73: H0A2 Index | H73: OAS_SPREAD_BID | I73: bps | J73: =IFERROR(INDEX(BDH($G$73,$H$73,'01_Parametros'!$B$3,'01_Parametros'!$B$3,"Days=A","Fill=B","Dir=H"),1,2),BDH($G$73,$H$73,'01_Parametros'!$B$3,'01_Parametros'!$B$3,"Days=A","Fill=B")) | K73: =IFERROR(INDEX(BDH($G$73,$H$73,'01_Parametros'!$B$5,'01_Parametros'!$B$5,"Days=A","Fill=B","Dir=H"),1,2),BDH($G$73,$H$73,'01_Parametros'!$B$5,'01_Parametros'!$B$5,"Days=A","Fill=B")) | L73: =IFERROR(INDEX(BDH($G$73,$H$73,'01_Parametros'!$B$6,'01_Parametros'!$B$6,"Days=A","Fill=B","Dir=H"),1,2),BDH($G$73,$H$73,'01_Parametros'!$B$6,'01_Parametros'!$B$6,"Days=A","Fill=B")) | M73: =IFERROR(INDEX(BDH($G$73,$H$73,'01_Parametros'!$B$7,'01_Parametros'!$B$7,"Days=A","Fill=B","Dir=H"),1,2),BDH($G$73,$H$73,'01_Parametros'!$B$7,'01_Parametros'!$B$7,"Days=A","Fill=B")) | N73: ICE BofA US HY Single-B OAS
A74: 73 | B74: credit_index | C74: US | D74: ICE_H0A3_CCC_OAS | E74: ALL | F74: 0 | G74: H0A3 Index | H74: OAS_SPREAD_BID | I74: bps | J74: =IFERROR(INDEX(BDH($G$74,$H$74,'01_Parametros'!$B$3,'01_Parametros'!$B$3,"Days=A","Fill=B","Dir=H"),1,2),BDH($G$74,$H$74,'01_Parametros'!$B$3,'01_Parametros'!$B$3,"Days=A","Fill=B")) | K74: =IFERROR(INDEX(BDH($G$74,$H$74,'01_Parametros'!$B$5,'01_Parametros'!$B$5,"Days=A","Fill=B","Dir=H"),1,2),BDH($G$74,$H$74,'01_Parametros'!$B$5,'01_Parametros'!$B$5,"Days=A","Fill=B")) | L74: =IFERROR(INDEX(BDH($G$74,$H$74,'01_Parametros'!$B$6,'01_Parametros'!$B$6,"Days=A","Fill=B","Dir=H"),1,2),BDH($G$74,$H$74,'01_Parametros'!$B$6,'01_Parametros'!$B$6,"Days=A","Fill=B")) | M74: =IFERROR(INDEX(BDH($G$74,$H$74,'01_Parametros'!$B$7,'01_Parametros'!$B$7,"Days=A","Fill=B","Dir=H"),1,2),BDH($G$74,$H$74,'01_Parametros'!$B$7,'01_Parametros'!$B$7,"Days=A","Fill=B")) | N74: ICE BofA US HY CCC OAS
A75: 74 | B75: credit_index | C75: EM | D75: CEMBI_BROAD_SPRD | E75: ALL | F75: 0 | G75: JPCBBRDF Index | H75: PX_LAST | I75: bps | J75: =IFERROR(INDEX(BDH($G$75,$H$75,'01_Parametros'!$B$3,'01_Parametros'!$B$3,"Days=A","Fill=B","Dir=H"),1,2),BDH($G$75,$H$75,'01_Parametros'!$B$3,'01_Parametros'!$B$3,"Days=A","Fill=B")) | K75: =IFERROR(INDEX(BDH($G$75,$H$75,'01_Parametros'!$B$5,'01_Parametros'!$B$5,"Days=A","Fill=B","Dir=H"),1,2),BDH($G$75,$H$75,'01_Parametros'!$B$5,'01_Parametros'!$B$5,"Days=A","Fill=B")) | L75: =IFERROR(INDEX(BDH($G$75,$H$75,'01_Parametros'!$B$6,'01_Parametros'!$B$6,"Days=A","Fill=B","Dir=H"),1,2),BDH($G$75,$H$75,'01_Parametros'!$B$6,'01_Parametros'!$B$6,"Days=A","Fill=B")) | M75: =IFERROR(INDEX(BDH($G$75,$H$75,'01_Parametros'!$B$7,'01_Parametros'!$B$7,"Days=A","Fill=B","Dir=H"),1,2),BDH($G$75,$H$75,'01_Parametros'!$B$7,'01_Parametros'!$B$7,"Days=A","Fill=B")) | N75: CEMBI Broad Diversified spread — confirmar
A76: 75 | B76: credit_index | C76: LATAM | D76: CEMBI_LATAM_SPRD | E76: ALL | F76: 0 | G76: JPCBLATS Index | H76: PX_LAST | I76: bps | J76: =IFERROR(INDEX(BDH($G$76,$H$76,'01_Parametros'!$B$3,'01_Parametros'!$B$3,"Days=A","Fill=B","Dir=H"),1,2),BDH($G$76,$H$76,'01_Parametros'!$B$3,'01_Parametros'!$B$3,"Days=A","Fill=B")) | K76: =IFERROR(INDEX(BDH($G$76,$H$76,'01_Parametros'!$B$5,'01_Parametros'!$B$5,"Days=A","Fill=B","Dir=H"),1,2),BDH($G$76,$H$76,'01_Parametros'!$B$5,'01_Parametros'!$B$5,"Days=A","Fill=B")) | L76: =IFERROR(INDEX(BDH($G$76,$H$76,'01_Parametros'!$B$6,'01_Parametros'!$B$6,"Days=A","Fill=B","Dir=H"),1,2),BDH($G$76,$H$76,'01_Parametros'!$B$6,'01_Parametros'!$B$6,"Days=A","Fill=B")) | M76: =IFERROR(INDEX(BDH($G$76,$H$76,'01_Parametros'!$B$7,'01_Parametros'!$B$7,"Days=A","Fill=B","Dir=H"),1,2),BDH($G$76,$H$76,'01_Parametros'!$B$7,'01_Parametros'!$B$7,"Days=A","Fill=B")) | N76: CEMBI Latam spread — confirmar
A77: 76 | B77: fx | C77: VE | D77: USDVES_OFICIAL | E77: SPOT | F77: 0 | G77: USDVES Curncy | H77: PX_LAST | I77: rate | J77: =IFERROR(INDEX(BDH($G$77,$H$77,'01_Parametros'!$B$3,'01_Parametros'!$B$3,"Days=A","Fill=B","Dir=H"),1,2),BDH($G$77,$H$77,'01_Parametros'!$B$3,'01_Parametros'!$B$3,"Days=A","Fill=B")) | K77: =IFERROR(INDEX(BDH($G$77,$H$77,'01_Parametros'!$B$5,'01_Parametros'!$B$5,"Days=A","Fill=B","Dir=H"),1,2),BDH($G$77,$H$77,'01_Parametros'!$B$5,'01_Parametros'!$B$5,"Days=A","Fill=B")) | L77: =IFERROR(INDEX(BDH($G$77,$H$77,'01_Parametros'!$B$6,'01_Parametros'!$B$6,"Days=A","Fill=B","Dir=H"),1,2),BDH($G$77,$H$77,'01_Parametros'!$B$6,'01_Parametros'!$B$6,"Days=A","Fill=B")) | M77: =IFERROR(INDEX(BDH($G$77,$H$77,'01_Parametros'!$B$7,'01_Parametros'!$B$7,"Days=A","Fill=B","Dir=H"),1,2),BDH($G$77,$H$77,'01_Parametros'!$B$7,'01_Parametros'!$B$7,"Days=A","Fill=B")) | N77: USD/VES oficial BCV — si BBG lo tiene
A78: 77 | B78: swap_curve | C78: US | D78: SOFR_OIS | E78: 1Y | F78: 1 | G78: USOSFR1 BGN Curncy | H78: PX_LAST | I78: percent | J78: =IFERROR(INDEX(BDH($G$78,$H$78,'01_Parametros'!$B$3,'01_Parametros'!$B$3,"Days=A","Fill=B","Dir=H"),1,2),BDH($G$78,$H$78,'01_Parametros'!$B$3,'01_Parametros'!$B$3,"Days=A","Fill=B")) | K78: =IFERROR(INDEX(BDH($G$78,$H$78,'01_Parametros'!$B$5,'01_Parametros'!$B$5,"Days=A","Fill=B","Dir=H"),1,2),BDH($G$78,$H$78,'01_Parametros'!$B$5,'01_Parametros'!$B$5,"Days=A","Fill=B")) | L78: =IFERROR(INDEX(BDH($G$78,$H$78,'01_Parametros'!$B$6,'01_Parametros'!$B$6,"Days=A","Fill=B","Dir=H"),1,2),BDH($G$78,$H$78,'01_Parametros'!$B$6,'01_Parametros'!$B$6,"Days=A","Fill=B")) | M78: =IFERROR(INDEX(BDH($G$78,$H$78,'01_Parametros'!$B$7,'01_Parametros'!$B$7,"Days=A","Fill=B","Dir=H"),1,2),BDH($G$78,$H$78,'01_Parametros'!$B$7,'01_Parametros'!$B$7,"Days=A","Fill=B")) | N78: USD SOFR OIS 1Y
A79: 78 | B79: swap_curve | C79: US | D79: SOFR_OIS | E79: 3Y | F79: 3 | G79: USOSFR3 BGN Curncy | H79: PX_LAST | I79: percent | J79: =IFERROR(INDEX(BDH($G$79,$H$79,'01_Parametros'!$B$3,'01_Parametros'!$B$3,"Days=A","Fill=B","Dir=H"),1,2),BDH($G$79,$H$79,'01_Parametros'!$B$3,'01_Parametros'!$B$3,"Days=A","Fill=B")) | K79: =IFERROR(INDEX(BDH($G$79,$H$79,'01_Parametros'!$B$5,'01_Parametros'!$B$5,"Days=A","Fill=B","Dir=H"),1,2),BDH($G$79,$H$79,'01_Parametros'!$B$5,'01_Parametros'!$B$5,"Days=A","Fill=B")) | L79: =IFERROR(INDEX(BDH($G$79,$H$79,'01_Parametros'!$B$6,'01_Parametros'!$B$6,"Days=A","Fill=B","Dir=H"),1,2),BDH($G$79,$H$79,'01_Parametros'!$B$6,'01_Parametros'!$B$6,"Days=A","Fill=B")) | M79: =IFERROR(INDEX(BDH($G$79,$H$79,'01_Parametros'!$B$7,'01_Parametros'!$B$7,"Days=A","Fill=B","Dir=H"),1,2),BDH($G$79,$H$79,'01_Parametros'!$B$7,'01_Parametros'!$B$7,"Days=A","Fill=B")) | N79: USD SOFR OIS 3Y
A80: 79 | B80: fx_forward | C80: G10 | D80: EURUSD_FWD | E80: 1M | F80: 0.083 | G80: EUR1M BGN Curncy | H80: PX_LAST | I80: rate | J80: =IFERROR(INDEX(BDH($G$80,$H$80,'01_Parametros'!$B$3,'01_Parametros'!$B$3,"Days=A","Fill=B","Dir=H"),1,2),BDH($G$80,$H$80,'01_Parametros'!$B$3,'01_Parametros'!$B$3,"Days=A","Fill=B")) | K80: =IFERROR(INDEX(BDH($G$80,$H$80,'01_Parametros'!$B$5,'01_Parametros'!$B$5,"Days=A","Fill=B","Dir=H"),1,2),BDH($G$80,$H$80,'01_Parametros'!$B$5,'01_Parametros'!$B$5,"Days=A","Fill=B")) | L80: =IFERROR(INDEX(BDH($G$80,$H$80,'01_Parametros'!$B$6,'01_Parametros'!$B$6,"Days=A","Fill=B","Dir=H"),1,2),BDH($G$80,$H$80,'01_Parametros'!$B$6,'01_Parametros'!$B$6,"Days=A","Fill=B")) | M80: =IFERROR(INDEX(BDH($G$80,$H$80,'01_Parametros'!$B$7,'01_Parametros'!$B$7,"Days=A","Fill=B","Dir=H"),1,2),BDH($G$80,$H$80,'01_Parametros'!$B$7,'01_Parametros'!$B$7,"Days=A","Fill=B")) | N80: EUR/USD forward 1M
A81: 80 | B81: fx_forward | C81: G10 | D81: EURUSD_FWD | E81: 3M | F81: 0.25 | G81: EUR3M BGN Curncy | H81: PX_LAST | I81: rate | J81: =IFERROR(INDEX(BDH($G$81,$H$81,'01_Parametros'!$B$3,'01_Parametros'!$B$3,"Days=A","Fill=B","Dir=H"),1,2),BDH($G$81,$H$81,'01_Parametros'!$B$3,'01_Parametros'!$B$3,"Days=A","Fill=B")) | K81: =IFERROR(INDEX(BDH($G$81,$H$81,'01_Parametros'!$B$5,'01_Parametros'!$B$5,"Days=A","Fill=B","Dir=H"),1,2),BDH($G$81,$H$81,'01_Parametros'!$B$5,'01_Parametros'!$B$5,"Days=A","Fill=B")) | L81: =IFERROR(INDEX(BDH($G$81,$H$81,'01_Parametros'!$B$6,'01_Parametros'!$B$6,"Days=A","Fill=B","Dir=H"),1,2),BDH($G$81,$H$81,'01_Parametros'!$B$6,'01_Parametros'!$B$6,"Days=A","Fill=B")) | M81: =IFERROR(INDEX(BDH($G$81,$H$81,'01_Parametros'!$B$7,'01_Parametros'!$B$7,"Days=A","Fill=B","Dir=H"),1,2),BDH($G$81,$H$81,'01_Parametros'!$B$7,'01_Parametros'!$B$7,"Days=A","Fill=B")) | N81: EUR/USD forward 3M
A82: 81 | B82: fx_forward | C82: G10 | D82: EURUSD_FWD | E82: 6M | F82: 0.5 | G82: EUR6M BGN Curncy | H82: PX_LAST | I82: rate | J82: =IFERROR(INDEX(BDH($G$82,$H$82,'01_Parametros'!$B$3,'01_Parametros'!$B$3,"Days=A","Fill=B","Dir=H"),1,2),BDH($G$82,$H$82,'01_Parametros'!$B$3,'01_Parametros'!$B$3,"Days=A","Fill=B")) | K82: =IFERROR(INDEX(BDH($G$82,$H$82,'01_Parametros'!$B$5,'01_Parametros'!$B$5,"Days=A","Fill=B","Dir=H"),1,2),BDH($G$82,$H$82,'01_Parametros'!$B$5,'01_Parametros'!$B$5,"Days=A","Fill=B")) | L82: =IFERROR(INDEX(BDH($G$82,$H$82,'01_Parametros'!$B$6,'01_Parametros'!$B$6,"Days=A","Fill=B","Dir=H"),1,2),BDH($G$82,$H$82,'01_Parametros'!$B$6,'01_Parametros'!$B$6,"Days=A","Fill=B")) | M82: =IFERROR(INDEX(BDH($G$82,$H$82,'01_Parametros'!$B$7,'01_Parametros'!$B$7,"Days=A","Fill=B","Dir=H"),1,2),BDH($G$82,$H$82,'01_Parametros'!$B$7,'01_Parametros'!$B$7,"Days=A","Fill=B")) | N82: EUR/USD forward 6M
A83: 82 | B83: fx_forward | C83: G10 | D83: EURUSD_FWD | E83: 1Y | F83: 1 | G83: EUR12M BGN Curncy | H83: PX_LAST | I83: rate | J83: =IFERROR(INDEX(BDH($G$83,$H$83,'01_Parametros'!$B$3,'01_Parametros'!$B$3,"Days=A","Fill=B","Dir=H"),1,2),BDH($G$83,$H$83,'01_Parametros'!$B$3,'01_Parametros'!$B$3,"Days=A","Fill=B")) | K83: =IFERROR(INDEX(BDH($G$83,$H$83,'01_Parametros'!$B$5,'01_Parametros'!$B$5,"Days=A","Fill=B","Dir=H"),1,2),BDH($G$83,$H$83,'01_Parametros'!$B$5,'01_Parametros'!$B$5,"Days=A","Fill=B")) | L83: =IFERROR(INDEX(BDH($G$83,$H$83,'01_Parametros'!$B$6,'01_Parametros'!$B$6,"Days=A","Fill=B","Dir=H"),1,2),BDH($G$83,$H$83,'01_Parametros'!$B$6,'01_Parametros'!$B$6,"Days=A","Fill=B")) | M83: =IFERROR(INDEX(BDH($G$83,$H$83,'01_Parametros'!$B$7,'01_Parametros'!$B$7,"Days=A","Fill=B","Dir=H"),1,2),BDH($G$83,$H$83,'01_Parametros'!$B$7,'01_Parametros'!$B$7,"Days=A","Fill=B")) | N83: EUR/USD forward 1Y
A84: 83 | B84: fx_forward | C84: G10 | D84: EURUSD_FWD | E84: 2Y | F84: 2 | G84: EUR2Y BGN Curncy | H84: PX_LAST | I84: rate | J84: =IFERROR(INDEX(BDH($G$84,$H$84,'01_Parametros'!$B$3,'01_Parametros'!$B$3,"Days=A","Fill=B","Dir=H"),1,2),BDH($G$84,$H$84,'01_Parametros'!$B$3,'01_Parametros'!$B$3,"Days=A","Fill=B")) | K84: =IFERROR(INDEX(BDH($G$84,$H$84,'01_Parametros'!$B$5,'01_Parametros'!$B$5,"Days=A","Fill=B","Dir=H"),1,2),BDH($G$84,$H$84,'01_Parametros'!$B$5,'01_Parametros'!$B$5,"Days=A","Fill=B")) | L84: =IFERROR(INDEX(BDH($G$84,$H$84,'01_Parametros'!$B$6,'01_Parametros'!$B$6,"Days=A","Fill=B","Dir=H"),1,2),BDH($G$84,$H$84,'01_Parametros'!$B$6,'01_Parametros'!$B$6,"Days=A","Fill=B")) | M84: =IFERROR(INDEX(BDH($G$84,$H$84,'01_Parametros'!$B$7,'01_Parametros'!$B$7,"Days=A","Fill=B","Dir=H"),1,2),BDH($G$84,$H$84,'01_Parametros'!$B$7,'01_Parametros'!$B$7,"Days=A","Fill=B")) | N84: EUR/USD forward 2Y
A85: 84 | B85: fx_forward | C85: G10 | D85: EURUSD_FWD | E85: 3Y | F85: 3 | G85: EUR3Y BGN Curncy | H85: PX_LAST | I85: rate | J85: =IFERROR(INDEX(BDH($G$85,$H$85,'01_Parametros'!$B$3,'01_Parametros'!$B$3,"Days=A","Fill=B","Dir=H"),1,2),BDH($G$85,$H$85,'01_Parametros'!$B$3,'01_Parametros'!$B$3,"Days=A","Fill=B")) | K85: =IFERROR(INDEX(BDH($G$85,$H$85,'01_Parametros'!$B$5,'01_Parametros'!$B$5,"Days=A","Fill=B","Dir=H"),1,2),BDH($G$85,$H$85,'01_Parametros'!$B$5,'01_Parametros'!$B$5,"Days=A","Fill=B")) | L85: =IFERROR(INDEX(BDH($G$85,$H$85,'01_Parametros'!$B$6,'01_Parametros'!$B$6,"Days=A","Fill=B","Dir=H"),1,2),BDH($G$85,$H$85,'01_Parametros'!$B$6,'01_Parametros'!$B$6,"Days=A","Fill=B")) | M85: =IFERROR(INDEX(BDH($G$85,$H$85,'01_Parametros'!$B$7,'01_Parametros'!$B$7,"Days=A","Fill=B","Dir=H"),1,2),BDH($G$85,$H$85,'01_Parametros'!$B$7,'01_Parametros'!$B$7,"Days=A","Fill=B")) | N85: EUR/USD forward 3Y
A86: 85 | B86: fx_forward | C86: G10 | D86: EURUSD_FWD | E86: 4Y | F86: 4 | G86: EUR4Y BGN Curncy | H86: PX_LAST | I86: rate | J86: =IFERROR(INDEX(BDH($G$86,$H$86,'01_Parametros'!$B$3,'01_Parametros'!$B$3,"Days=A","Fill=B","Dir=H"),1,2),BDH($G$86,$H$86,'01_Parametros'!$B$3,'01_Parametros'!$B$3,"Days=A","Fill=B")) | K86: =IFERROR(INDEX(BDH($G$86,$H$86,'01_Parametros'!$B$5,'01_Parametros'!$B$5,"Days=A","Fill=B","Dir=H"),1,2),BDH($G$86,$H$86,'01_Parametros'!$B$5,'01_Parametros'!$B$5,"Days=A","Fill=B")) | L86: =IFERROR(INDEX(BDH($G$86,$H$86,'01_Parametros'!$B$6,'01_Parametros'!$B$6,"Days=A","Fill=B","Dir=H"),1,2),BDH($G$86,$H$86,'01_Parametros'!$B$6,'01_Parametros'!$B$6,"Days=A","Fill=B")) | M86: =IFERROR(INDEX(BDH($G$86,$H$86,'01_Parametros'!$B$7,'01_Parametros'!$B$7,"Days=A","Fill=B","Dir=H"),1,2),BDH($G$86,$H$86,'01_Parametros'!$B$7,'01_Parametros'!$B$7,"Days=A","Fill=B")) | N86: EUR/USD forward 4Y
A87: 86 | B87: fx_forward | C87: G10 | D87: EURUSD_FWD | E87: 5Y | F87: 5 | G87: EUR5Y BGN Curncy | H87: PX_LAST | I87: rate | J87: =IFERROR(INDEX(BDH($G$87,$H$87,'01_Parametros'!$B$3,'01_Parametros'!$B$3,"Days=A","Fill=B","Dir=H"),1,2),BDH($G$87,$H$87,'01_Parametros'!$B$3,'01_Parametros'!$B$3,"Days=A","Fill=B")) | K87: =IFERROR(INDEX(BDH($G$87,$H$87,'01_Parametros'!$B$5,'01_Parametros'!$B$5,"Days=A","Fill=B","Dir=H"),1,2),BDH($G$87,$H$87,'01_Parametros'!$B$5,'01_Parametros'!$B$5,"Days=A","Fill=B")) | L87: =IFERROR(INDEX(BDH($G$87,$H$87,'01_Parametros'!$B$6,'01_Parametros'!$B$6,"Days=A","Fill=B","Dir=H"),1,2),BDH($G$87,$H$87,'01_Parametros'!$B$6,'01_Parametros'!$B$6,"Days=A","Fill=B")) | M87: =IFERROR(INDEX(BDH($G$87,$H$87,'01_Parametros'!$B$7,'01_Parametros'!$B$7,"Days=A","Fill=B","Dir=H"),1,2),BDH($G$87,$H$87,'01_Parametros'!$B$7,'01_Parametros'!$B$7,"Days=A","Fill=B")) | N87: EUR/USD forward 5Y
A88: 87 | B88: fx_forward | C88: G10 | D88: GBPUSD_FWD | E88: 1M | F88: 0.083 | G88: GBP1M BGN Curncy | H88: PX_LAST | I88: rate | J88: =IFERROR(INDEX(BDH($G$88,$H$88,'01_Parametros'!$B$3,'01_Parametros'!$B$3,"Days=A","Fill=B","Dir=H"),1,2),BDH($G$88,$H$88,'01_Parametros'!$B$3,'01_Parametros'!$B$3,"Days=A","Fill=B")) | K88: =IFERROR(INDEX(BDH($G$88,$H$88,'01_Parametros'!$B$5,'01_Parametros'!$B$5,"Days=A","Fill=B","Dir=H"),1,2),BDH($G$88,$H$88,'01_Parametros'!$B$5,'01_Parametros'!$B$5,"Days=A","Fill=B")) | L88: =IFERROR(INDEX(BDH($G$88,$H$88,'01_Parametros'!$B$6,'01_Parametros'!$B$6,"Days=A","Fill=B","Dir=H"),1,2),BDH($G$88,$H$88,'01_Parametros'!$B$6,'01_Parametros'!$B$6,"Days=A","Fill=B")) | M88: =IFERROR(INDEX(BDH($G$88,$H$88,'01_Parametros'!$B$7,'01_Parametros'!$B$7,"Days=A","Fill=B","Dir=H"),1,2),BDH($G$88,$H$88,'01_Parametros'!$B$7,'01_Parametros'!$B$7,"Days=A","Fill=B")) | N88: GBP/USD forward 1M
A89: 88 | B89: fx_forward | C89: G10 | D89: GBPUSD_FWD | E89: 3M | F89: 0.25 | G89: GBP3M BGN Curncy | H89: PX_LAST | I89: rate | J89: =IFERROR(INDEX(BDH($G$89,$H$89,'01_Parametros'!$B$3,'01_Parametros'!$B$3,"Days=A","Fill=B","Dir=H"),1,2),BDH($G$89,$H$89,'01_Parametros'!$B$3,'01_Parametros'!$B$3,"Days=A","Fill=B")) | K89: =IFERROR(INDEX(BDH($G$89,$H$89,'01_Parametros'!$B$5,'01_Parametros'!$B$5,"Days=A","Fill=B","Dir=H"),1,2),BDH($G$89,$H$89,'01_Parametros'!$B$5,'01_Parametros'!$B$5,"Days=A","Fill=B")) | L89: =IFERROR(INDEX(BDH($G$89,$H$89,'01_Parametros'!$B$6,'01_Parametros'!$B$6,"Days=A","Fill=B","Dir=H"),1,2),BDH($G$89,$H$89,'01_Parametros'!$B$6,'01_Parametros'!$B$6,"Days=A","Fill=B")) | M89: =IFERROR(INDEX(BDH($G$89,$H$89,'01_Parametros'!$B$7,'01_Parametros'!$B$7,"Days=A","Fill=B","Dir=H"),1,2),BDH($G$89,$H$89,'01_Parametros'!$B$7,'01_Parametros'!$B$7,"Days=A","Fill=B")) | N89: GBP/USD forward 3M
A90: 89 | B90: fx_forward | C90: G10 | D90: GBPUSD_FWD | E90: 6M | F90: 0.5 | G90: GBP6M BGN Curncy | H90: PX_LAST | I90: rate | J90: =IFERROR(INDEX(BDH($G$90,$H$90,'01_Parametros'!$B$3,'01_Parametros'!$B$3,"Days=A","Fill=B","Dir=H"),1,2),BDH($G$90,$H$90,'01_Parametros'!$B$3,'01_Parametros'!$B$3,"Days=A","Fill=B")) | K90: =IFERROR(INDEX(BDH($G$90,$H$90,'01_Parametros'!$B$5,'01_Parametros'!$B$5,"Days=A","Fill=B","Dir=H"),1,2),BDH($G$90,$H$90,'01_Parametros'!$B$5,'01_Parametros'!$B$5,"Days=A","Fill=B")) | L90: =IFERROR(INDEX(BDH($G$90,$H$90,'01_Parametros'!$B$6,'01_Parametros'!$B$6,"Days=A","Fill=B","Dir=H"),1,2),BDH($G$90,$H$90,'01_Parametros'!$B$6,'01_Parametros'!$B$6,"Days=A","Fill=B")) | M90: =IFERROR(INDEX(BDH($G$90,$H$90,'01_Parametros'!$B$7,'01_Parametros'!$B$7,"Days=A","Fill=B","Dir=H"),1,2),BDH($G$90,$H$90,'01_Parametros'!$B$7,'01_Parametros'!$B$7,"Days=A","Fill=B")) | N90: GBP/USD forward 6M
A91: 90 | B91: fx_forward | C91: G10 | D91: GBPUSD_FWD | E91: 1Y | F91: 1 | G91: GBP12M BGN Curncy | H91: PX_LAST | I91: rate | J91: =IFERROR(INDEX(BDH($G$91,$H$91,'01_Parametros'!$B$3,'01_Parametros'!$B$3,"Days=A","Fill=B","Dir=H"),1,2),BDH($G$91,$H$91,'01_Parametros'!$B$3,'01_Parametros'!$B$3,"Days=A","Fill=B")) | K91: =IFERROR(INDEX(BDH($G$91,$H$91,'01_Parametros'!$B$5,'01_Parametros'!$B$5,"Days=A","Fill=B","Dir=H"),1,2),BDH($G$91,$H$91,'01_Parametros'!$B$5,'01_Parametros'!$B$5,"Days=A","Fill=B")) | L91: =IFERROR(INDEX(BDH($G$91,$H$91,'01_Parametros'!$B$6,'01_Parametros'!$B$6,"Days=A","Fill=B","Dir=H"),1,2),BDH($G$91,$H$91,'01_Parametros'!$B$6,'01_Parametros'!$B$6,"Days=A","Fill=B")) | M91: =IFERROR(INDEX(BDH($G$91,$H$91,'01_Parametros'!$B$7,'01_Parametros'!$B$7,"Days=A","Fill=B","Dir=H"),1,2),BDH($G$91,$H$91,'01_Parametros'!$B$7,'01_Parametros'!$B$7,"Days=A","Fill=B")) | N91: GBP/USD forward 1Y
A92: 91 | B92: fx_forward | C92: G10 | D92: GBPUSD_FWD | E92: 2Y | F92: 2 | G92: GBP2Y BGN Curncy | H92: PX_LAST | I92: rate | J92: =IFERROR(INDEX(BDH($G$92,$H$92,'01_Parametros'!$B$3,'01_Parametros'!$B$3,"Days=A","Fill=B","Dir=H"),1,2),BDH($G$92,$H$92,'01_Parametros'!$B$3,'01_Parametros'!$B$3,"Days=A","Fill=B")) | K92: =IFERROR(INDEX(BDH($G$92,$H$92,'01_Parametros'!$B$5,'01_Parametros'!$B$5,"Days=A","Fill=B","Dir=H"),1,2),BDH($G$92,$H$92,'01_Parametros'!$B$5,'01_Parametros'!$B$5,"Days=A","Fill=B")) | L92: =IFERROR(INDEX(BDH($G$92,$H$92,'01_Parametros'!$B$6,'01_Parametros'!$B$6,"Days=A","Fill=B","Dir=H"),1,2),BDH($G$92,$H$92,'01_Parametros'!$B$6,'01_Parametros'!$B$6,"Days=A","Fill=B")) | M92: =IFERROR(INDEX(BDH($G$92,$H$92,'01_Parametros'!$B$7,'01_Parametros'!$B$7,"Days=A","Fill=B","Dir=H"),1,2),BDH($G$92,$H$92,'01_Parametros'!$B$7,'01_Parametros'!$B$7,"Days=A","Fill=B")) | N92: GBP/USD forward 2Y
A93: 92 | B93: fx_forward | C93: G10 | D93: GBPUSD_FWD | E93: 3Y | F93: 3 | G93: GBP3Y BGN Curncy | H93: PX_LAST | I93: rate | J93: =IFERROR(INDEX(BDH($G$93,$H$93,'01_Parametros'!$B$3,'01_Parametros'!$B$3,"Days=A","Fill=B","Dir=H"),1,2),BDH($G$93,$H$93,'01_Parametros'!$B$3,'01_Parametros'!$B$3,"Days=A","Fill=B")) | K93: =IFERROR(INDEX(BDH($G$93,$H$93,'01_Parametros'!$B$5,'01_Parametros'!$B$5,"Days=A","Fill=B","Dir=H"),1,2),BDH($G$93,$H$93,'01_Parametros'!$B$5,'01_Parametros'!$B$5,"Days=A","Fill=B")) | L93: =IFERROR(INDEX(BDH($G$93,$H$93,'01_Parametros'!$B$6,'01_Parametros'!$B$6,"Days=A","Fill=B","Dir=H"),1,2),BDH($G$93,$H$93,'01_Parametros'!$B$6,'01_Parametros'!$B$6,"Days=A","Fill=B")) | M93: =IFERROR(INDEX(BDH($G$93,$H$93,'01_Parametros'!$B$7,'01_Parametros'!$B$7,"Days=A","Fill=B","Dir=H"),1,2),BDH($G$93,$H$93,'01_Parametros'!$B$7,'01_Parametros'!$B$7,"Days=A","Fill=B")) | N93: GBP/USD forward 3Y
A94: 93 | B94: fx_forward | C94: G10 | D94: GBPUSD_FWD | E94: 4Y | F94: 4 | G94: GBP4Y BGN Curncy | H94: PX_LAST | I94: rate | J94: =IFERROR(INDEX(BDH($G$94,$H$94,'01_Parametros'!$B$3,'01_Parametros'!$B$3,"Days=A","Fill=B","Dir=H"),1,2),BDH($G$94,$H$94,'01_Parametros'!$B$3,'01_Parametros'!$B$3,"Days=A","Fill=B")) | K94: =IFERROR(INDEX(BDH($G$94,$H$94,'01_Parametros'!$B$5,'01_Parametros'!$B$5,"Days=A","Fill=B","Dir=H"),1,2),BDH($G$94,$H$94,'01_Parametros'!$B$5,'01_Parametros'!$B$5,"Days=A","Fill=B")) | L94: =IFERROR(INDEX(BDH($G$94,$H$94,'01_Parametros'!$B$6,'01_Parametros'!$B$6,"Days=A","Fill=B","Dir=H"),1,2),BDH($G$94,$H$94,'01_Parametros'!$B$6,'01_Parametros'!$B$6,"Days=A","Fill=B")) | M94: =IFERROR(INDEX(BDH($G$94,$H$94,'01_Parametros'!$B$7,'01_Parametros'!$B$7,"Days=A","Fill=B","Dir=H"),1,2),BDH($G$94,$H$94,'01_Parametros'!$B$7,'01_Parametros'!$B$7,"Days=A","Fill=B")) | N94: GBP/USD forward 4Y
A95: 94 | B95: fx_forward | C95: G10 | D95: GBPUSD_FWD | E95: 5Y | F95: 5 | G95: GBP5Y BGN Curncy | H95: PX_LAST | I95: rate | J95: =IFERROR(INDEX(BDH($G$95,$H$95,'01_Parametros'!$B$3,'01_Parametros'!$B$3,"Days=A","Fill=B","Dir=H"),1,2),BDH($G$95,$H$95,'01_Parametros'!$B$3,'01_Parametros'!$B$3,"Days=A","Fill=B")) | K95: =IFERROR(INDEX(BDH($G$95,$H$95,'01_Parametros'!$B$5,'01_Parametros'!$B$5,"Days=A","Fill=B","Dir=H"),1,2),BDH($G$95,$H$95,'01_Parametros'!$B$5,'01_Parametros'!$B$5,"Days=A","Fill=B")) | L95: =IFERROR(INDEX(BDH($G$95,$H$95,'01_Parametros'!$B$6,'01_Parametros'!$B$6,"Days=A","Fill=B","Dir=H"),1,2),BDH($G$95,$H$95,'01_Parametros'!$B$6,'01_Parametros'!$B$6,"Days=A","Fill=B")) | M95: =IFERROR(INDEX(BDH($G$95,$H$95,'01_Parametros'!$B$7,'01_Parametros'!$B$7,"Days=A","Fill=B","Dir=H"),1,2),BDH($G$95,$H$95,'01_Parametros'!$B$7,'01_Parametros'!$B$7,"Days=A","Fill=B")) | N95: GBP/USD forward 5Y
A96: 95 | B96: fx_forward | C96: G10 | D96: USDJPY_FWD | E96: 1M | F96: 0.083 | G96: JPY1M BGN Curncy | H96: PX_LAST | I96: rate | J96: =IFERROR(INDEX(BDH($G$96,$H$96,'01_Parametros'!$B$3,'01_Parametros'!$B$3,"Days=A","Fill=B","Dir=H"),1,2),BDH($G$96,$H$96,'01_Parametros'!$B$3,'01_Parametros'!$B$3,"Days=A","Fill=B")) | K96: =IFERROR(INDEX(BDH($G$96,$H$96,'01_Parametros'!$B$5,'01_Parametros'!$B$5,"Days=A","Fill=B","Dir=H"),1,2),BDH($G$96,$H$96,'01_Parametros'!$B$5,'01_Parametros'!$B$5,"Days=A","Fill=B")) | L96: =IFERROR(INDEX(BDH($G$96,$H$96,'01_Parametros'!$B$6,'01_Parametros'!$B$6,"Days=A","Fill=B","Dir=H"),1,2),BDH($G$96,$H$96,'01_Parametros'!$B$6,'01_Parametros'!$B$6,"Days=A","Fill=B")) | M96: =IFERROR(INDEX(BDH($G$96,$H$96,'01_Parametros'!$B$7,'01_Parametros'!$B$7,"Days=A","Fill=B","Dir=H"),1,2),BDH($G$96,$H$96,'01_Parametros'!$B$7,'01_Parametros'!$B$7,"Days=A","Fill=B")) | N96: USD/JPY forward 1M
A97: 96 | B97: fx_forward | C97: G10 | D97: USDJPY_FWD | E97: 3M | F97: 0.25 | G97: JPY3M BGN Curncy | H97: PX_LAST | I97: rate | J97: =IFERROR(INDEX(BDH($G$97,$H$97,'01_Parametros'!$B$3,'01_Parametros'!$B$3,"Days=A","Fill=B","Dir=H"),1,2),BDH($G$97,$H$97,'01_Parametros'!$B$3,'01_Parametros'!$B$3,"Days=A","Fill=B")) | K97: =IFERROR(INDEX(BDH($G$97,$H$97,'01_Parametros'!$B$5,'01_Parametros'!$B$5,"Days=A","Fill=B","Dir=H"),1,2),BDH($G$97,$H$97,'01_Parametros'!$B$5,'01_Parametros'!$B$5,"Days=A","Fill=B")) | L97: =IFERROR(INDEX(BDH($G$97,$H$97,'01_Parametros'!$B$6,'01_Parametros'!$B$6,"Days=A","Fill=B","Dir=H"),1,2),BDH($G$97,$H$97,'01_Parametros'!$B$6,'01_Parametros'!$B$6,"Days=A","Fill=B")) | M97: =IFERROR(INDEX(BDH($G$97,$H$97,'01_Parametros'!$B$7,'01_Parametros'!$B$7,"Days=A","Fill=B","Dir=H"),1,2),BDH($G$97,$H$97,'01_Parametros'!$B$7,'01_Parametros'!$B$7,"Days=A","Fill=B")) | N97: USD/JPY forward 3M
A98: 97 | B98: fx_forward | C98: G10 | D98: USDJPY_FWD | E98: 6M | F98: 0.5 | G98: JPY6M BGN Curncy | H98: PX_LAST | I98: rate | J98: =IFERROR(INDEX(BDH($G$98,$H$98,'01_Parametros'!$B$3,'01_Parametros'!$B$3,"Days=A","Fill=B","Dir=H"),1,2),BDH($G$98,$H$98,'01_Parametros'!$B$3,'01_Parametros'!$B$3,"Days=A","Fill=B")) | K98: =IFERROR(INDEX(BDH($G$98,$H$98,'01_Parametros'!$B$5,'01_Parametros'!$B$5,"Days=A","Fill=B","Dir=H"),1,2),BDH($G$98,$H$98,'01_Parametros'!$B$5,'01_Parametros'!$B$5,"Days=A","Fill=B")) | L98: =IFERROR(INDEX(BDH($G$98,$H$98,'01_Parametros'!$B$6,'01_Parametros'!$B$6,"Days=A","Fill=B","Dir=H"),1,2),BDH($G$98,$H$98,'01_Parametros'!$B$6,'01_Parametros'!$B$6,"Days=A","Fill=B")) | M98: =IFERROR(INDEX(BDH($G$98,$H$98,'01_Parametros'!$B$7,'01_Parametros'!$B$7,"Days=A","Fill=B","Dir=H"),1,2),BDH($G$98,$H$98,'01_Parametros'!$B$7,'01_Parametros'!$B$7,"Days=A","Fill=B")) | N98: USD/JPY forward 6M
A99: 98 | B99: fx_forward | C99: G10 | D99: USDJPY_FWD | E99: 1Y | F99: 1 | G99: JPY12M BGN Curncy | H99: PX_LAST | I99: rate | J99: =IFERROR(INDEX(BDH($G$99,$H$99,'01_Parametros'!$B$3,'01_Parametros'!$B$3,"Days=A","Fill=B","Dir=H"),1,2),BDH($G$99,$H$99,'01_Parametros'!$B$3,'01_Parametros'!$B$3,"Days=A","Fill=B")) | K99: =IFERROR(INDEX(BDH($G$99,$H$99,'01_Parametros'!$B$5,'01_Parametros'!$B$5,"Days=A","Fill=B","Dir=H"),1,2),BDH($G$99,$H$99,'01_Parametros'!$B$5,'01_Parametros'!$B$5,"Days=A","Fill=B")) | L99: =IFERROR(INDEX(BDH($G$99,$H$99,'01_Parametros'!$B$6,'01_Parametros'!$B$6,"Days=A","Fill=B","Dir=H"),1,2),BDH($G$99,$H$99,'01_Parametros'!$B$6,'01_Parametros'!$B$6,"Days=A","Fill=B")) | M99: =IFERROR(INDEX(BDH($G$99,$H$99,'01_Parametros'!$B$7,'01_Parametros'!$B$7,"Days=A","Fill=B","Dir=H"),1,2),BDH($G$99,$H$99,'01_Parametros'!$B$7,'01_Parametros'!$B$7,"Days=A","Fill=B")) | N99: USD/JPY forward 1Y
A100: 99 | B100: fx_forward | C100: G10 | D100: USDJPY_FWD | E100: 2Y | F100: 2 | G100: JPY2Y BGN Curncy | H100: PX_LAST | I100: rate | J100: =IFERROR(INDEX(BDH($G$100,$H$100,'01_Parametros'!$B$3,'01_Parametros'!$B$3,"Days=A","Fill=B","Dir=H"),1,2),BDH($G$100,$H$100,'01_Parametros'!$B$3,'01_Parametros'!$B$3,"Days=A","Fill=B")) | K100: =IFERROR(INDEX(BDH($G$100,$H$100,'01_Parametros'!$B$5,'01_Parametros'!$B$5,"Days=A","Fill=B","Dir=H"),1,2),BDH($G$100,$H$100,'01_Parametros'!$B$5,'01_Parametros'!$B$5,"Days=A","Fill=B")) | L100: =IFERROR(INDEX(BDH($G$100,$H$100,'01_Parametros'!$B$6,'01_Parametros'!$B$6,"Days=A","Fill=B","Dir=H"),1,2),BDH($G$100,$H$100,'01_Parametros'!$B$6,'01_Parametros'!$B$6,"Days=A","Fill=B")) | M100: =IFERROR(INDEX(BDH($G$100,$H$100,'01_Parametros'!$B$7,'01_Parametros'!$B$7,"Days=A","Fill=B","Dir=H"),1,2),BDH($G$100,$H$100,'01_Parametros'!$B$7,'01_Parametros'!$B$7,"Days=A","Fill=B")) | N100: USD/JPY forward 2Y
...

Sheet 03_SOFR_Futures
A1: # | B1: contract_code | C1: description | D1: AS_OF_price | E1: AS_OF_implied_rate | F1: MES_ANT_price | G1: MES_ANT_implied_rate | H1: open_interest
A2: 1 | B2: SFR1 Comdty | C2: SOFR future month 1 | D2: =IFERROR(INDEX(BDH($B$2,"PX_LAST",'01_Parametros'!$B$3,'01_Parametros'!$B$3,"Days=A","Fill=B"),1,2),BDH($B$2,"PX_LAST",'01_Parametros'!$B$3,'01_Parametros'!$B$3,"Days=A","Fill=B")) | E2: =100-D2 | F2: =IFERROR(INDEX(BDH($B$2,"PX_LAST",'01_Parametros'!$B$5,'01_Parametros'!$B$5,"Days=A","Fill=B"),1,2),BDH($B$2,"PX_LAST",'01_Parametros'!$B$5,'01_Parametros'!$B$5,"Days=A","Fill=B")) | G2: =100-F2 | H2: =IFERROR(INDEX(BDH($B$2,"OPEN_INT",'01_Parametros'!$B$3,'01_Parametros'!$B$3,"Days=A","Fill=B"),1,2),BDH($B$2,"OPEN_INT",'01_Parametros'!$B$3,'01_Parametros'!$B$3,"Days=A","Fill=B"))
A3: 2 | B3: SFR2 Comdty | C3: SOFR future month 2 | D3: =IFERROR(INDEX(BDH($B$3,"PX_LAST",'01_Parametros'!$B$3,'01_Parametros'!$B$3,"Days=A","Fill=B"),1,2),BDH($B$3,"PX_LAST",'01_Parametros'!$B$3,'01_Parametros'!$B$3,"Days=A","Fill=B")) | E3: =100-D3 | F3: =IFERROR(INDEX(BDH($B$3,"PX_LAST",'01_Parametros'!$B$5,'01_Parametros'!$B$5,"Days=A","Fill=B"),1,2),BDH($B$3,"PX_LAST",'01_Parametros'!$B$5,'01_Parametros'!$B$5,"Days=A","Fill=B")) | G3: =100-F3 | H3: =IFERROR(INDEX(BDH($B$3,"OPEN_INT",'01_Parametros'!$B$3,'01_Parametros'!$B$3,"Days=A","Fill=B"),1,2),BDH($B$3,"OPEN_INT",'01_Parametros'!$B$3,'01_Parametros'!$B$3,"Days=A","Fill=B"))
A4: 3 | B4: SFR3 Comdty | C4: SOFR future month 3 | D4: =IFERROR(INDEX(BDH($B$4,"PX_LAST",'01_Parametros'!$B$3,'01_Parametros'!$B$3,"Days=A","Fill=B"),1,2),BDH($B$4,"PX_LAST",'01_Parametros'!$B$3,'01_Parametros'!$B$3,"Days=A","Fill=B")) | E4: =100-D4 | F4: =IFERROR(INDEX(BDH($B$4,"PX_LAST",'01_Parametros'!$B$5,'01_Parametros'!$B$5,"Days=A","Fill=B"),1,2),BDH($B$4,"PX_LAST",'01_Parametros'!$B$5,'01_Parametros'!$B$5,"Days=A","Fill=B")) | G4: =100-F4 | H4: =IFERROR(INDEX(BDH($B$4,"OPEN_INT",'01_Parametros'!$B$3,'01_Parametros'!$B$3,"Days=A","Fill=B"),1,2),BDH($B$4,"OPEN_INT",'01_Parametros'!$B$3,'01_Parametros'!$B$3,"Days=A","Fill=B"))
A5: 4 | B5: SFR4 Comdty | C5: SOFR future month 4 | D5: =IFERROR(INDEX(BDH($B$5,"PX_LAST",'01_Parametros'!$B$3,'01_Parametros'!$B$3,"Days=A","Fill=B"),1,2),BDH($B$5,"PX_LAST",'01_Parametros'!$B$3,'01_Parametros'!$B$3,"Days=A","Fill=B")) | E5: =100-D5 | F5: =IFERROR(INDEX(BDH($B$5,"PX_LAST",'01_Parametros'!$B$5,'01_Parametros'!$B$5,"Days=A","Fill=B"),1,2),BDH($B$5,"PX_LAST",'01_Parametros'!$B$5,'01_Parametros'!$B$5,"Days=A","Fill=B")) | G5: =100-F5 | H5: =IFERROR(INDEX(BDH($B$5,"OPEN_INT",'01_Parametros'!$B$3,'01_Parametros'!$B$3,"Days=A","Fill=B"),1,2),BDH($B$5,"OPEN_INT",'01_Parametros'!$B$3,'01_Parametros'!$B$3,"Days=A","Fill=B"))
A6: 5 | B6: SFR5 Comdty | C6: SOFR future month 5 | D6: =IFERROR(INDEX(BDH($B$6,"PX_LAST",'01_Parametros'!$B$3,'01_Parametros'!$B$3,"Days=A","Fill=B"),1,2),BDH($B$6,"PX_LAST",'01_Parametros'!$B$3,'01_Parametros'!$B$3,"Days=A","Fill=B")) | E6: =100-D6 | F6: =IFERROR(INDEX(BDH($B$6,"PX_LAST",'01_Parametros'!$B$5,'01_Parametros'!$B$5,"Days=A","Fill=B"),1,2),BDH($B$6,"PX_LAST",'01_Parametros'!$B$5,'01_Parametros'!$B$5,"Days=A","Fill=B")) | G6: =100-F6 | H6: =IFERROR(INDEX(BDH($B$6,"OPEN_INT",'01_Parametros'!$B$3,'01_Parametros'!$B$3,"Days=A","Fill=B"),1,2),BDH($B$6,"OPEN_INT",'01_Parametros'!$B$3,'01_Parametros'!$B$3,"Days=A","Fill=B"))
A7: 6 | B7: SFR6 Comdty | C7: SOFR future month 6 | D7: =IFERROR(INDEX(BDH($B$7,"PX_LAST",'01_Parametros'!$B$3,'01_Parametros'!$B$3,"Days=A","Fill=B"),1,2),BDH($B$7,"PX_LAST",'01_Parametros'!$B$3,'01_Parametros'!$B$3,"Days=A","Fill=B")) | E7: =100-D7 | F7: =IFERROR(INDEX(BDH($B$7,"PX_LAST",'01_Parametros'!$B$5,'01_Parametros'!$B$5,"Days=A","Fill=B"),1,2),BDH($B$7,"PX_LAST",'01_Parametros'!$B$5,'01_Parametros'!$B$5,"Days=A","Fill=B")) | G7: =100-F7 | H7: =IFERROR(INDEX(BDH($B$7,"OPEN_INT",'01_Parametros'!$B$3,'01_Parametros'!$B$3,"Days=A","Fill=B"),1,2),BDH($B$7,"OPEN_INT",'01_Parametros'!$B$3,'01_Parametros'!$B$3,"Days=A","Fill=B"))
A8: 7 | B8: SFR7 Comdty | C8: SOFR future month 7 | D8: =IFERROR(INDEX(BDH($B$8,"PX_LAST",'01_Parametros'!$B$3,'01_Parametros'!$B$3,"Days=A","Fill=B"),1,2),BDH($B$8,"PX_LAST",'01_Parametros'!$B$3,'01_Parametros'!$B$3,"Days=A","Fill=B")) | E8: =100-D8 | F8: =IFERROR(INDEX(BDH($B$8,"PX_LAST",'01_Parametros'!$B$5,'01_Parametros'!$B$5,"Days=A","Fill=B"),1,2),BDH($B$8,"PX_LAST",'01_Parametros'!$B$5,'01_Parametros'!$B$5,"Days=A","Fill=B")) | G8: =100-F8 | H8: =IFERROR(INDEX(BDH($B$8,"OPEN_INT",'01_Parametros'!$B$3,'01_Parametros'!$B$3,"Days=A","Fill=B"),1,2),BDH($B$8,"OPEN_INT",'01_Parametros'!$B$3,'01_Parametros'!$B$3,"Days=A","Fill=B"))
A9: 8 | B9: SFR8 Comdty | C9: SOFR future month 8 | D9: =IFERROR(INDEX(BDH($B$9,"PX_LAST",'01_Parametros'!$B$3,'01_Parametros'!$B$3,"Days=A","Fill=B"),1,2),BDH($B$9,"PX_LAST",'01_Parametros'!$B$3,'01_Parametros'!$B$3,"Days=A","Fill=B")) | E9: =100-D9 | F9: =IFERROR(INDEX(BDH($B$9,"PX_LAST",'01_Parametros'!$B$5,'01_Parametros'!$B$5,"Days=A","Fill=B"),1,2),BDH($B$9,"PX_LAST",'01_Parametros'!$B$5,'01_Parametros'!$B$5,"Days=A","Fill=B")) | G9: =100-F9 | H9: =IFERROR(INDEX(BDH($B$9,"OPEN_INT",'01_Parametros'!$B$3,'01_Parametros'!$B$3,"Days=A","Fill=B"),1,2),BDH($B$9,"OPEN_INT",'01_Parametros'!$B$3,'01_Parametros'!$B$3,"Days=A","Fill=B"))
A12: Nota | B12: SFRn Comdty = continuous front-month rolling future n (n=1 es el primer vencimiento activo).
B13: Implied rate = 100 - price (convencion CME).
B14: Si el ticker continuous no esta disponible, sustituir por el codigo del contrato especifico (ej. SFRZ6 Comdty para dic-2026).

Sheet 04_FedWatch
A1: FedWatch — paste manual desde pantalla WIRP de Bloomberg
A2: Pegar como valores. Esta hoja NO tiene formulas BDP.
A4: meeting_date | B4: current_rate_implied | C4: prob_-50bps | D4: prob_-25bps | E4: prob_0bps | F4: prob_+25bps | G4: prob_+50bps | H4: notas

Sheet 05_Notas_Analista
A1: Notas del analista
A3: Cualquier observacion: tickers que fallaron, eventos del mes, anomalias, sugerencias.
A5: Tickers fallidos / corregidos
A6: —
A7: —
A8: —
A9: —
A10: —
A11: —
A12: —
A13: —
A14: —
... A29: Sugerencias para el corte siguiente

Sheet 99_Envio
A1: Como devolver este archivo
A3: OPCION 1 — Recomendada — Upload directo a GitHub (web)
A4: 1. Guardar el archivo con nombre: BloombergTemplate_TasasMercantil_<YYYY-MM>.xlsx
A5: 2. En el navegador (incluido movil) ir a: github.com/andresborrerom/credito_Panama
A6: 3. Cambiar al branch: claude/tasas-mercantil-report-Q8sFt
A7: 4. Navegar a la carpeta: ProyectoTasasMercantil/cortes/<YYYY-MM>/input/
A8: (si no existe, crearla con 'Add file -> Create new file' y nombre 'input/.gitkeep')
A9: 5. 'Add file' -> 'Upload files' -> arrastrar el xlsx
A10: 6. Commit message sugerido: 'ingest(corte YYYY-MM): input Bloomberg cargado por <analista>'
A11: 7. Click 'Commit changes'.
A13: OPCION 2 — Correo electronico
A14: Enviar el .xlsx por correo al equipo (Andres + Camilo + Claude session si aplica).
... A24: Si el archivo paso validacion, llega confirmacion. Si fallo, llega lista de campos a revisar.
